{"1":{"dur":1,"text":"RONALD SMITH: Well,\nI'm talking about storms, but"},"2":{"dur":3,"text":"someone asked me a question the\nother day about why the"},"6":{"dur":2,"text":"Coriolis force is opposite\nin the two hemispheres."},"8":{"dur":3,"text":"And I can't give you a complete\nexplanation, but I"},"12":{"dur":4,"text":"can give you a partial\nexplanation."},"16":{"dur":3,"text":"Here's the globe, and of course,\nit spins toward the"},"19":{"dur":3,"text":"east. The sun rises in the east,\nsets in the west. So"},"23":{"dur":2,"text":"that's the way the\nEarth spins."},"26":{"dur":3,"text":"If I keep spinning it in that\ndirection and I face this"},"29":{"dur":3,"text":"towards you, is that clockwise\nor counterclockwise?"},"35":{"dur":1,"text":"Counterclockwise."},"36":{"dur":4,"text":"I'm going to keep spinning\nit in that direction."},"40":{"dur":3,"text":"Is that clockwise or\ncounterclockwise?"},"43":{"dur":1,"text":"Clockwise."},"45":{"dur":7,"text":"So in a sense, while the globe\nspins eastward, the sense of"},"52":{"dur":4,"text":"rotation is opposite in\nthe two hemispheres."},"57":{"dur":3,"text":"And that is one way to\nunderstand why the Coriolis"},"60":{"dur":3,"text":"force is opposite in the\ntwo hemispheres."},"63":{"dur":3,"text":"So like I said, not a complete\nexplanation, but it's true,"},"67":{"dur":5,"text":"and I think it helps to\nunderstand that tricky point"},"72":{"dur":2,"text":"about the Coriolis force."},"75":{"dur":1,"text":"Any questions on that?"},"80":{"dur":3,"text":"So we're going through\nstorms today."},"83":{"dur":3,"text":"This is not very quantitative\nmaterial."},"87":{"dur":2,"text":"This stuff will be posted\nafter the fact, and your"},"89":{"dur":1,"text":"textbook is very good."},"91":{"dur":2,"text":"These chapters that I've\nassigned, a number of them"},"93":{"dur":4,"text":"have to do with storm\ntypes and so on."},"98":{"dur":1,"text":"So you'll find a good-- of\ncourse, I will explain things"},"99":{"dur":3,"text":"somewhat differently, but you'll\nfind a good way to get"},"102":{"dur":3,"text":"competing views of this by\nlistening to what I say and"},"105":{"dur":2,"text":"then reading the textbook, and\nbetween the two, you should"},"108":{"dur":4,"text":"come out pretty well\non this subject."},"113":{"dur":11,"text":"So we were talking about\nconvective storms. And that is"},"124":{"dur":4,"text":"the class of storms that get\ntheir energy from the release"},"128":{"dur":1,"text":"of latent heat."},"129":{"dur":1,"text":"I mentioned this last time."},"131":{"dur":1,"text":"That's a number that I carry\naround in my head."},"133":{"dur":3,"text":"It's rounded off a little bit,\nbut I use that number so often"},"137":{"dur":1,"text":"that I carry it around\nin my head."},"138":{"dur":3,"text":"The latent heat of condensation,\nor if you like,"},"141":{"dur":1,"text":"the latent heat of\nevaporation--"},"143":{"dur":3,"text":"it's the same magnitude,\nindependent of whether you're"},"147":{"dur":3,"text":"condensing or evaporating\nwater-- is about 2 and 1\/2"},"150":{"dur":2,"text":"million joules per kilogram."},"153":{"dur":4,"text":"And so when you condense water,\nyou're then providing"},"157":{"dur":4,"text":"extra heat to the air, which\nmakes it warmer, more buoyant."},"162":{"dur":5,"text":"It's likely to rise then, and\nthat's what's going on in all"},"168":{"dur":2,"text":"of these storms. It's the basic"},"170":{"dur":1,"text":"underlying energy source."},"172":{"dur":2,"text":"We talked about air-mass\nthunderstorms last time and"},"174":{"dur":3,"text":"how they go through\na life cycle."},"177":{"dur":1,"text":"And after--"},"179":{"dur":4,"text":"they take about 20 minutes to\n30 minutes to develop from a"},"183":{"dur":4,"text":"fair-weather cumulus into a\ncumulonimbus with rain coming"},"188":{"dur":1,"text":"out the bottom."},"189":{"dur":3,"text":"And then as the rain begins,\nyou begin to get some"},"193":{"dur":3,"text":"evaporation of falling\nrainwater"},"196":{"dur":2,"text":"just below cloud base."},"198":{"dur":4,"text":"That produces cool air, which\nthen sinks and spreads out."},"203":{"dur":4,"text":"It's like you open your freezer\ndoor, and that cold"},"207":{"dur":3,"text":"air from the freezer falls down\nto the kitchen floor and"},"210":{"dur":1,"text":"then spreads out."},"212":{"dur":3,"text":"That's what's happening, and\nthat goes by various names."},"215":{"dur":4,"text":"Sometimes we call it a\ndownburst. Sometimes it's"},"219":{"dur":2,"text":"called a gust front."},"222":{"dur":1,"text":"The front of it is called\nthe gust front."},"223":{"dur":3,"text":"But anyway, the air is now\nspreading out away from the"},"226":{"dur":4,"text":"cloud, and that shuts off\nthe warm, moist inflow."},"231":{"dur":3,"text":"So it kills itself\noff, basically."},"234":{"dur":1,"text":"It has a-- after about\ntwo hours, it's gone."},"236":{"dur":4,"text":"Now, that outflow might well\ntrigger another thunderstorm."},"240":{"dur":2,"text":"So that doesn't mean, for\nexample, over the state of"},"242":{"dur":2,"text":"Connecticut on a day when there\nare thunderstorms, it"},"245":{"dur":3,"text":"doesn't mean there's just going\nto be one and then none."},"249":{"dur":2,"text":"It means there'll be one, and\nthen as it dies, it may"},"251":{"dur":2,"text":"trigger two others, and\nthen as they die,"},"253":{"dur":1,"text":"they may trigger others."},"255":{"dur":3,"text":"So this may go on throughout\nthe afternoon, but the"},"258":{"dur":4,"text":"individual cells have\na short lifetime."},"263":{"dur":1,"text":"That's an important\ncharacteristic."},"265":{"dur":5,"text":"As opposed to these severe\nstorms, which have the"},"271":{"dur":5,"text":"additional environmental factor\nof having wind shear"},"277":{"dur":4,"text":"through the troposphere, usually\na jet stream aloft."},"281":{"dur":2,"text":"Strong winds near the\ntropopause, weak winds near"},"283":{"dur":3,"text":"the surface of the Earth, that\ntends to bend the storm over"},"287":{"dur":5,"text":"and change its structure into\none in which the inflow is at"},"293":{"dur":3,"text":"a different location than the\noutflow caused by that"},"296":{"dur":1,"text":"evaporative cooling."},"297":{"dur":3,"text":"In fact, the cold air generated\nby evaporative"},"301":{"dur":4,"text":"cooling spreads out and actually\nforms a gust front"},"305":{"dur":2,"text":"over which the warm\nair then lifts."},"307":{"dur":3,"text":"So it actually assists in the\nlifting of the warm air up"},"311":{"dur":0,"text":"into the cloud."},"312":{"dur":4,"text":"And this structure is more or\nless stable and can persist"},"316":{"dur":2,"text":"for a number of hours\nand in some cases"},"318":{"dur":2,"text":"even for even overnight."},"321":{"dur":1,"text":"And these are the\nones that have--"},"323":{"dur":2,"text":"they're larger and\nthey're severe in"},"325":{"dur":1,"text":"every way you can imagine."},"327":{"dur":2,"text":"I think I showed these\nlast time."},"329":{"dur":2,"text":"But heavy rains and\nflooding, hail,"},"331":{"dur":2,"text":"lightning, tornadic winds."},"334":{"dur":3,"text":"I don't think the low pressure\nin the tornado is much of an"},"338":{"dur":3,"text":"issue, but the gust-front winds\ncoming from that cool"},"341":{"dur":4,"text":"air is another source\nof wind damage."},"345":{"dur":3,"text":"In many-- in some cases, that\ncauses more damage than even a"},"349":{"dur":0,"text":"tornado could."},"350":{"dur":3,"text":"Usually, the tornadic winds are\nstronger when there is a"},"353":{"dur":4,"text":"tornado, but the gust-front\nwinds may cover a wider area"},"358":{"dur":2,"text":"and in some cases will\ncause more damage"},"360":{"dur":2,"text":"than a possible tornado."},"366":{"dur":2,"text":"I don't know if I got\nthis far, but here's"},"369":{"dur":0,"text":"a picture of one."},"370":{"dur":2,"text":"And earlier in the course, we\ntalked about the visual"},"373":{"dur":3,"text":"appearance of a funnel."},"377":{"dur":2,"text":"And this is called the\ncondensation funnel."},"379":{"dur":7,"text":"That is basically a cloud\ncomposed of tiny liquid water"},"386":{"dur":7,"text":"droplets that's produced when\nair from outside moves in and"},"394":{"dur":1,"text":"drops its pressure."},"395":{"dur":5,"text":"The pressure inside a tornado\nis much lower than in the"},"400":{"dur":2,"text":"surrounding atmosphere, so that\nair that moves in there"},"402":{"dur":3,"text":"is going to expand, not by\nmoving vertically, but by"},"406":{"dur":2,"text":"moving into the tornado."},"408":{"dur":3,"text":"It'll expand, cool, and\nyou can form a cloud."},"411":{"dur":0,"text":"And that's what you're seeing."},"412":{"dur":2,"text":"In fact, you often see this\ndescending from cloud base."},"415":{"dur":3,"text":"The cloud base will appear to\nbe flat, and then as the"},"419":{"dur":2,"text":"tornado develops, that\nfunnel cloud will"},"421":{"dur":1,"text":"descend to the ground."},"423":{"dur":3,"text":"When you see that, it's more\nnatural to understand that"},"426":{"dur":2,"text":"it's really like a cloud,\nbecause it's actually an"},"429":{"dur":3,"text":"extension of that cloud reaching\ndown to the surface."},"432":{"dur":2,"text":"Whereas this other thing here\nis the debris funnel."},"435":{"dur":4,"text":"That's stuff that's been kicked\nup by the high winds at"},"439":{"dur":1,"text":"the surface, and that's\nnot water."},"441":{"dur":4,"text":"That's usually dirt or soil or\ncows or cars or houses and"},"446":{"dur":1,"text":"things like that."},"449":{"dur":3,"text":"And here again, you see the\ncondensation funnel, and you"},"453":{"dur":2,"text":"see a debris funnel\naround that."},"459":{"dur":1,"text":"Lightning comes along\nwith that."},"461":{"dur":4,"text":"And of course, these sparks of\nelectricity is what you hear"},"465":{"dur":1,"text":"as thunder."},"469":{"dur":2,"text":"And I think you know that-- how\nmany know how to compute"},"471":{"dur":2,"text":"in your mind how\nfar a storm is?"},"473":{"dur":2,"text":"Do you know that trick?"},"476":{"dur":3,"text":"It's pretty simple, because you\nassume that the light that"},"479":{"dur":5,"text":"comes from the lightning strike\ntravels to your eye at"},"484":{"dur":2,"text":"the speed of light, which\nis, you might say,"},"487":{"dur":2,"text":"instantaneous, right?"},"489":{"dur":5,"text":"Whereas the sound that reaches\nyour ear moves at the speed of"},"495":{"dur":4,"text":"sound, which is something like\n300 meters per second."},"499":{"dur":4,"text":"And so if you simply-- when you\nsee a lightning flash, if"},"503":{"dur":3,"text":"you then count out the\nnumber of seconds--"},"507":{"dur":1,"text":"one second, two seconds--"},"509":{"dur":4,"text":"so for every second delay\nbetween the two, that's 300"},"513":{"dur":1,"text":"meters of distance."},"514":{"dur":4,"text":"So if it was three seconds\ndelayed, that would be 900"},"518":{"dur":2,"text":"meters or about a kilometer\naway from you."},"521":{"dur":3,"text":"So that's an easy calculation\nto do, realizing that the"},"525":{"dur":3,"text":"thunder is produced by\nthe lightning itself."},"528":{"dur":3,"text":"You suddenly heat that air with\nthe electrical discharge,"},"532":{"dur":4,"text":"it expands suddenly, produces\nan acoustic signal that then"},"537":{"dur":6,"text":"travels to your ear, and you\nrecognize that as thunder."},"543":{"dur":1,"text":"Questions on that?"},"547":{"dur":4,"text":"Hailstones, because there's a\nlot of supercooled water above"},"552":{"dur":3,"text":"the freezing line in those\nstorms and very strong updraft"},"556":{"dur":3,"text":"motions that can suspend\nparticles while"},"559":{"dur":2,"text":"they grow by riming."},"562":{"dur":3,"text":"And eventually, when either that\nupdraft weakens or the"},"566":{"dur":2,"text":"object becomes too\nlarge, it'll then"},"568":{"dur":1,"text":"fall out of the sky."},"569":{"dur":3,"text":"And it's too large to melt."},"572":{"dur":3,"text":"I told you many times that a\nsnowflake will melt as it"},"576":{"dur":1,"text":"passes down through\nthe freezing level"},"577":{"dur":1,"text":"and become a raindrop."},"579":{"dur":4,"text":"But if I've got a chunk of ice\nthat's five centimeters across"},"583":{"dur":2,"text":"and it falls down,\nit's too big."},"585":{"dur":2,"text":"It's going to take\nminutes to melt."},"588":{"dur":2,"text":"And by that time, it'll\nbe at the surface."},"591":{"dur":4,"text":"It'll be wet, it'll have a wet\nouter surface, but it'll still"},"595":{"dur":3,"text":"be a solid chunk of ice when\nit falls to Earth and hits."},"605":{"dur":3,"text":"This is thunderstorm frequency\nacross the United States,"},"608":{"dur":3,"text":"number of thunderstorms\nper year."},"612":{"dur":1,"text":"Now, I've told you that\nthese are called--"},"613":{"dur":2,"text":"most of these are just air-mass\nthunderstorms."},"616":{"dur":2,"text":"They're not so damaging."},"618":{"dur":5,"text":"And it looks like Florida is\nthe capital for air-mass"},"624":{"dur":4,"text":"thunderstorms. You get\n100 of them per year."},"628":{"dur":3,"text":"Other areas get far less."},"631":{"dur":1,"text":"But these aren't the\nsevere ones."},"633":{"dur":2,"text":"I'll show you the severe\nones in just a moment."},"635":{"dur":2,"text":"You don't get many thunderstorms\nin the West"},"637":{"dur":5,"text":"Coast, because there's too\nstrong an inversion there."},"643":{"dur":3,"text":"Theres a temp-- normally, with\nthe cold water off the coast"},"646":{"dur":3,"text":"from the California Current,\nthe atmosphere over here is"},"649":{"dur":4,"text":"just too stable, too many\ninversions to get"},"654":{"dur":3,"text":"thunderstorms forming in\nthat part of the world."},"657":{"dur":2,"text":"So it really is kind of an\nEast Coast phenomenon."},"660":{"dur":2,"text":"But it starts right at the Rocky\nMountain Front here in"},"663":{"dur":4,"text":"Colorado, and you find storms\nthen pretty much all the way"},"667":{"dur":2,"text":"to the east, including all the\nway up into Canada you get"},"669":{"dur":2,"text":"quite a few."},"672":{"dur":4,"text":"Now, I don't often in this\ncourse talk about the research"},"677":{"dur":3,"text":"that goes on here at Yale or in\nmy group, but I wanted to"},"681":{"dur":1,"text":"show you one thing."},"682":{"dur":3,"text":"I had a Ph.D. Student who\nfinished a couple of years ago"},"686":{"dur":4,"text":"who tried to understand the\ntiming of thunderstorms from"},"690":{"dur":1,"text":"west to east across--"},"692":{"dur":2,"text":"in a region generally\nlike this."},"694":{"dur":3,"text":"And so she looked at\na lot of climate--"},"698":{"dur":5,"text":"of rainfall data from the summer\nmonths and came up with"},"704":{"dur":1,"text":"a diagram like this."},"705":{"dur":1,"text":"Now, I'm going to\nexplain this."},"706":{"dur":2,"text":"It's going to take a minute just\nto figure out what in the"},"708":{"dur":1,"text":"heck is plotted here."},"709":{"dur":2,"text":"But on this axis is longitude."},"712":{"dur":4,"text":"So it's distance east-west\nbasically through a region"},"717":{"dur":0,"text":"something like this."},"718":{"dur":3,"text":"So it's the distance east-west\nin a latitude belt"},"721":{"dur":2,"text":"something like that."},"723":{"dur":3,"text":"And on this axis is the\nlocal solar time."},"727":{"dur":3,"text":"So instead of actually using\ntime zones, which are kind of"},"730":{"dur":1,"text":"an artificial construct--"},"732":{"dur":3,"text":"they make arbitrary choices\nabout where to switch from"},"735":{"dur":2,"text":"Eastern Time to Central Time\nto Mountain Time--"},"738":{"dur":1,"text":"this is just local time."},"739":{"dur":3,"text":"Basically, how high is the sun\nin the sky, that determines"},"743":{"dur":2,"text":"what this clock would be."},"745":{"dur":3,"text":"And then contoured is the\nprecipitation rate, the hourly"},"749":{"dur":1,"text":"precipitation rate."},"750":{"dur":3,"text":"So from this diagram, for any\ngiven latitude, if you scan"},"754":{"dur":2,"text":"up, you'll find how much\nit rains at different"},"757":{"dur":0,"text":"hours of the day."},"758":{"dur":2,"text":"Now, we did repeat."},"760":{"dur":1,"text":"We plotted everything twice."},"761":{"dur":3,"text":"So you've got zero to 24\nand then 24 to 48."},"765":{"dur":3,"text":"But if you notice, the plot\njust repeats as well."},"768":{"dur":3,"text":"So we've just put the same data\non there twice, which"},"771":{"dur":2,"text":"makes it a little bit\neasier to go through"},"773":{"dur":2,"text":"a full day's cycle."},"775":{"dur":3,"text":"You can start at any hour you\nwant and go 24 hours ahead."},"779":{"dur":2,"text":"So this is the Rocky\nMountain Front."},"781":{"dur":4,"text":"This is where a lot of\nthunderstorms form."},"786":{"dur":1,"text":"It's over in here."},"788":{"dur":6,"text":"And those storms tend to form\nbetween 1200 and 1800."},"794":{"dur":3,"text":"So that's in the afternoon,\nlocal solar time."},"797":{"dur":1,"text":"Now, that's not a\nsurprise, right?"},"798":{"dur":2,"text":"Because one of the most\nimportant triggers for"},"801":{"dur":4,"text":"thunderstorms is the heating\nof the Earth by the Sun."},"806":{"dur":4,"text":"So it's in the afternoon when\nyou've built up this deep"},"810":{"dur":2,"text":"convective boundary layer\nby heating the"},"812":{"dur":1,"text":"surface of the Earth."},"814":{"dur":3,"text":"And finally, that heating is\ngoing to generate cumulus"},"817":{"dur":2,"text":"clouds, and they'll then grow\nto form cumulonimbus."},"820":{"dur":2,"text":"So it's not surprising\nthat you find"},"822":{"dur":1,"text":"storms beginning there."},"823":{"dur":2,"text":"And over the East Coast-- here\nin Connecticut, for example--"},"826":{"dur":6,"text":"you also find that the storms\nform in the afternoon, due to"},"833":{"dur":1,"text":"the heating of the\nEarth by the Sun."},"835":{"dur":5,"text":"But look what happens in this\nmiddle territory, which is"},"840":{"dur":4,"text":"basically this very large\nregion through here."},"844":{"dur":2,"text":"That has some other kind of a\ntrigger, because, look, that"},"847":{"dur":2,"text":"is advancing in time."},"849":{"dur":4,"text":"As I move eastward, the time\nof day when thunderstorms"},"854":{"dur":4,"text":"occur is 6 o'clock, 9 o'clock\nin the evening, midnight, 3"},"858":{"dur":2,"text":"o'clock in the morning,\n6 o'clock the next"},"861":{"dur":0,"text":"morning, and so on."},"862":{"dur":3,"text":"So you've got something that is\ndeparting from the simple"},"865":{"dur":3,"text":"idea of the Sun as the\ndriving force."},"869":{"dur":3,"text":"What this turns out to be is a\ndisturbance that's generated"},"873":{"dur":3,"text":"each day over the Rocky\nMountains and then is--"},"876":{"dur":1,"text":"whoops, wrong direction--"},"878":{"dur":4,"text":"and then is pushed eastwards\nby the westerly winds."},"882":{"dur":3,"text":"And it's a warm air disturbance"},"886":{"dur":1,"text":"generated over the mountains."},"887":{"dur":3,"text":"And as it drifts eastward\naloft, it triggers"},"891":{"dur":3,"text":"thunderstorms as\nit moves along."},"894":{"dur":2,"text":"I had somebody in my office\na couple of weeks ago, a"},"896":{"dur":4,"text":"scientist who grew up in one\nof these states and always"},"901":{"dur":3,"text":"wondered why there they had a\nmaximum thunderstorm frequency"},"905":{"dur":0,"text":"in the middle of the night."},"906":{"dur":1,"text":"Who would expect that?"},"907":{"dur":3,"text":"It doesn't seem to fit with\nthe standard thermal solar"},"910":{"dur":0,"text":"forcing idea."},"911":{"dur":0,"text":"Well, this is why."},"912":{"dur":2,"text":"In this case, my student\ndiscovered that it's a"},"915":{"dur":2,"text":"disturbance generated over the\nRockies that moves eastward"},"917":{"dur":3,"text":"and gives that progressive\ntiming to the thunderstorms."},"921":{"dur":3,"text":"Then you get east of the\nAppalachian Mountains, and you"},"925":{"dur":3,"text":"get back to a more normal\nmid-afternoon"},"928":{"dur":2,"text":"thunderstorm maxima."},"930":{"dur":1,"text":"Any questions on that?"},"932":{"dur":2,"text":"STUDENT: What are those\ndotted lines?"},"934":{"dur":1,"text":"PROFESSOR: I think\nthey're reference lines"},"936":{"dur":4,"text":"for some other figure in the\npaper that's not shown here."},"941":{"dur":2,"text":"So there are sloping lines\nthat are drawn in here at"},"944":{"dur":1,"text":"different speeds."},"945":{"dur":4,"text":"Since this is distance versus\ntime, a slope represents a"},"949":{"dur":1,"text":"propagation speed--"},"951":{"dur":3,"text":"30 meters per second, 14 meters\nper second, seven"},"954":{"dur":0,"text":"meters per second."},"955":{"dur":3,"text":"These disturbances move eastward\nat about 14 meters"},"958":{"dur":4,"text":"per second, bringing those\nthunderstorms progressively"},"963":{"dur":1,"text":"later as you move"},"964":{"dur":1,"text":"towards the east. Yes."},"965":{"dur":3,"text":"STUDENT: Was it already known\nthat there was a warm weather"},"969":{"dur":3,"text":"air disturbance over\nthe Rockies, or did"},"973":{"dur":2,"text":"PROFESSOR: No, that's not shown in this"},"975":{"dur":1,"text":"figure, but that\nwas actually--"},"977":{"dur":4,"text":"there was some hint about this\nprogression already from radar"},"981":{"dur":3,"text":"data, but she confirmed\nit using surface data."},"984":{"dur":3,"text":"And then she discovered this\nwarm air pulse aloft that was"},"987":{"dur":1,"text":"doing the triggering."},"989":{"dur":3,"text":"That was the point of\nher thesis, yeah."},"992":{"dur":1,"text":"Anything else on that?"},"997":{"dur":2,"text":"So now let's get to the severe\nthunderstorms. And the way"},"1000":{"dur":2,"text":"I'll get at that is just to\nshow you this tornado"},"1003":{"dur":3,"text":"frequency map."},"1006":{"dur":1,"text":"And of course, it looks\na bit different."},"1008":{"dur":3,"text":"There is a maximum in Florida,\nbut it's smaller."},"1012":{"dur":3,"text":"And the big maximum\nis over Texas,"},"1015":{"dur":2,"text":"Oklahoma, Kansas, Nebraska."},"1018":{"dur":3,"text":"And of course, this is\nwhat's called Tornado"},"1021":{"dur":1,"text":"Alley by some people."},"1023":{"dur":1,"text":"You've heard that expression."},"1024":{"dur":0,"text":"It's kind of the region."},"1025":{"dur":2,"text":"But what's special about this\nregion apparently-- and by the"},"1028":{"dur":3,"text":"way, this maximizes\nin the spring."},"1031":{"dur":5,"text":"So typically, this is an\nApril-May phenomenon."},"1036":{"dur":3,"text":"If you have watched any of\nthese shows about chasing"},"1040":{"dur":3,"text":"tornadoes and if you want to\ndo that, then schedule your"},"1043":{"dur":3,"text":"trip in April and May, because\nthat's when things get"},"1047":{"dur":2,"text":"exciting out there."},"1049":{"dur":3,"text":"And what's special about this\nregion is that you get some"},"1053":{"dur":3,"text":"warm, moist air moving in from\nthe Gulf of Mexico at low"},"1056":{"dur":4,"text":"levels, and then you get the jet\nstream coming across the"},"1060":{"dur":1,"text":"Rocky Mountains at\nhigh levels."},"1062":{"dur":3,"text":"And that gives you the\nshear that you need."},"1066":{"dur":2,"text":"And you've got the moisture,\nbecause you've got the high"},"1068":{"dur":2,"text":"temperatures and high humidities\nin the low levels."},"1071":{"dur":2,"text":"So all the ingredients\nare kind of there."},"1074":{"dur":2,"text":"Not every day-- it fluctuates\nfrom day to day-- but"},"1077":{"dur":3,"text":"generally, that's the reason why\nthis area is so special."},"1080":{"dur":4,"text":"And as far as I know, there's\nno other place on Earth that"},"1084":{"dur":3,"text":"has as many-- as high a tornado\nfrequency as this"},"1088":{"dur":2,"text":"So this is special even\nif you look globally."},"1091":{"dur":3,"text":"There are a few other places in\nAsia and in Australia where"},"1095":{"dur":3,"text":"they get this phenomenon, but\nthis is kind of the most"},"1098":{"dur":4,"text":"frequent place for\nit to occur."},"1103":{"dur":2,"text":"Questions there?"},"1105":{"dur":2,"text":"Anybody from Tornado Alley?"},"1108":{"dur":2,"text":"Anybody live in these states?"},"1110":{"dur":1,"text":"Not at all?"},"1112":{"dur":3,"text":"You're all East Coast or\nWest Coast people?"},"1115":{"dur":0,"text":"Yeah."},"1116":{"dur":2,"text":"STUDENT: The little spots in the\nSoutheast, is there-- is"},"1118":{"dur":1,"text":"that a coincidence?"},"1121":{"dur":1,"text":"PROFESSOR: Yeah,\nthat's a good question."},"1123":{"dur":3,"text":"For example, I read a paper once\nabout this one, who tried"},"1127":{"dur":3,"text":"to claim there was something\nspecial about the terrain in"},"1131":{"dur":0,"text":"that region."},"1132":{"dur":2,"text":"But to be honest with you, I\nwould doubt the statistical"},"1134":{"dur":3,"text":"significance of something like\nthat, unless I really had seen"},"1137":{"dur":3,"text":"a very rigorous statistical\nanalysis."},"1140":{"dur":3,"text":"I would wonder whether these\nspots are really realistic or"},"1144":{"dur":2,"text":"whether they're just a fluke\nof what-- and he had one or"},"1147":{"dur":3,"text":"two events there, and by random\nchance, that happened"},"1150":{"dur":2,"text":"to look like a little maximum\nor something like that."},"1152":{"dur":4,"text":"So I wouldn't try to put too\nmuch significance on those."},"1156":{"dur":1,"text":"Whether that-- that may be\ndistinct from this one."},"1158":{"dur":2,"text":"I think the case could\nbe made there."},"1160":{"dur":1,"text":"But I'm not sure why."},"1162":{"dur":5,"text":"I'm not sure why there would\nbe two maxima there."},"1167":{"dur":3,"text":"We do get them in Connecticut\nas well."},"1171":{"dur":2,"text":"Not frequently, but every few\nyears, we get a tornado that"},"1173":{"dur":1,"text":"comes down through the state."},"1175":{"dur":2,"text":"It can cause quite\na bit of damage."},"1178":{"dur":4,"text":"But it's like a ratio of 7:1\nor 9:1 in terms of the"},"1182":{"dur":5,"text":"relative frequency of\nthose two things."},"1187":{"dur":2,"text":"So before we leave the subject,\nI want to give you a"},"1190":{"dur":4,"text":"little bit of a sense for\nwhat a tornado is like."},"1194":{"dur":4,"text":"And here's a picture from May\n2007, the devastation in"},"1199":{"dur":1,"text":"Greensburg, Kansas."},"1200":{"dur":1,"text":"Really a whole town was--"},"1202":{"dur":1,"text":"isn't that horrible?"},"1203":{"dur":1,"text":"It's just everything\nwiped out."},"1204":{"dur":2,"text":"And the only way I could think\nof-- and this is going to take"},"1207":{"dur":3,"text":"a couple minutes and may be a\nlittle bit boring-- we'll"},"1211":{"dur":3,"text":"see-- but I want to show you\nwhat the news was saying at"},"1215":{"dur":1,"text":"this point."},"1220":{"dur":1,"text":"So this is--"},"1241":{"dur":2,"text":"this is the radar, the\nDoppler radar--"},"1244":{"dur":2,"text":"I'll explain why that's\nimportant in just a minute--"},"1246":{"dur":1,"text":"blue-red."},"1253":{"dur":0,"text":"[VIDEO PLAYBACK]"},"1254":{"dur":1,"text":"-So keep in mind, as far\nas looking through the"},"1255":{"dur":2,"text":"thunderstorm and seeing the\ntornado appear in Greensburg,"},"1258":{"dur":2,"text":"you're not going to, because\nit's going to be obscured by"},"1260":{"dur":3,"text":"the very heavy rain and also the\nhail between you and that"},"1264":{"dur":0,"text":"circulation."},"1265":{"dur":2,"text":"Greenburg's up here at the\ntop of the screen."},"1267":{"dur":1,"text":"-And when we switch\nover to the"},"1268":{"dur":2,"text":"which-way-the-wind's-blowing\nmode to the"},"1270":{"dur":2,"text":"how-hard-it's-raining mode,\nthis is what we have now."},"1272":{"dur":2,"text":"And you can see that very\nhigh reflectivity."},"1274":{"dur":1,"text":"What you see is that red."},"1276":{"dur":2,"text":"That is the heavy\nrain and hail."},"1279":{"dur":2,"text":"So you're not going to be able\nto visualize the thunderstorm"},"1281":{"dur":1,"text":"if it's still producing\na tornado."},"1283":{"dur":2,"text":"-Now, contact with Lanny Dean,\nwe temporarily lost it because"},"1286":{"dur":2,"text":"of the cell service in this\npart of Kansas, but once"},"1288":{"dur":2,"text":"again, you're seeing a very\nstrong, very well-pronounced"},"1290":{"dur":3,"text":"hook echo in addition to the\nvery strong velocity returns--"},"1293":{"dur":0,"text":"[END VIDEO PLAYBACK]"},"1294":{"dur":2,"text":"PROFESSOR: That's\nthe hook echo right there."},"1297":{"dur":1,"text":"-The city of Greensburg and to\nthe south, I really suggest"},"1299":{"dur":2,"text":"you go down to your\nstorm shelters."},"1301":{"dur":1,"text":"I said I'm not an alarmist kind\nof guy, but if the only"},"1303":{"dur":2,"text":"thing-- this storm\nis very scary--"},"1305":{"dur":2,"text":"in the worst case, I'm just\ngoing to waste a little bit of"},"1307":{"dur":2,"text":"your time tonight if you go down\nto your shelters and it"},"1310":{"dur":2,"text":"turns out not to be producing\na tornado."},"1312":{"dur":1,"text":"But just what we're\nseeing here is"},"1314":{"dur":1,"text":"a very scary signature."},"1318":{"dur":1,"text":"-Lanny, how close are you\nto the county line?"},"1320":{"dur":3,"text":"-We have passed the county\nline already, Jay."},"1323":{"dur":2,"text":"-So you're north of the county\nline, and the tornado, from"},"1325":{"dur":3,"text":"your vantage point, is to the\neast of US 183, correct?"},"1328":{"dur":2,"text":"-Jay, a very large tornado."},"1331":{"dur":2,"text":"OK, I don't know who reported\nit in the west. We have two"},"1333":{"dur":1,"text":"tornadoes on the ground, Jay."},"1335":{"dur":3,"text":"We have a small-- well, excuse\nme it's a medium, if you will,"},"1338":{"dur":5,"text":"to my north-northeast. We have\na very large wedge tornado on"},"1344":{"dur":1,"text":"the ground that's going\nto be almost"},"1345":{"dur":1,"text":"due north of my location."},"1347":{"dur":3,"text":"I'm going to put it about five\nmiles, Jay, about five miles,"},"1351":{"dur":3,"text":"I'm guessing, north, maybe five\nto eight miles north of"},"1354":{"dur":1,"text":"my location right now, Jay."},"1355":{"dur":1,"text":"-All right, Landy, try\nto get the first cam"},"1357":{"dur":1,"text":"fired up if you can."},"1359":{"dur":2,"text":"And, Darren, what do you see\nfrom your vantage point?"},"1362":{"dur":2,"text":"-Right now, we're just about\nready to get on the Highway"},"1364":{"dur":3,"text":"183 to go north towards\nGreensburg."},"1368":{"dur":3,"text":"We still have a large wedge\ntornado on the ground to our"},"1371":{"dur":2,"text":"north with possible satellite\ntornadoes."},"1374":{"dur":5,"text":"We just saw a lightning flash\nthat still probably--"},"1379":{"dur":3,"text":"I would say probably five miles\nto our north is where"},"1382":{"dur":1,"text":"the tornado would be located."},"1383":{"dur":4,"text":"And it has been on the ground\nfor probably 25 minutes, maybe"},"1388":{"dur":1,"text":"[END VIDEO PLAYBCK]"},"1390":{"dur":1,"text":"PROFESSOR: It's moving in that direction."},"1391":{"dur":1,"text":"[VIDEO PLAYBACK]"},"1392":{"dur":0,"text":"-What cross-street?"},"1393":{"dur":2,"text":"How far north of the\nKiowa-Comanche"},"1395":{"dur":1,"text":"county line are you?"},"1396":{"dur":1,"text":"-We're right on the line."},"1398":{"dur":1,"text":"-You're right on the\nline currently."},"1399":{"dur":1,"text":"And you're about to\nproceed northbound"},"1401":{"dur":1,"text":"back behind the tornado?"},"1402":{"dur":1,"text":"-That's correct."},"1403":{"dur":1,"text":"-And you've been watching this\nfor quite a little while."},"1405":{"dur":3,"text":"And what did you estimate\nits maximum width was?"},"1408":{"dur":3,"text":"-I would say easily a mile,\nand that's kind of being"},"1412":{"dur":1,"text":"conservative."},"1413":{"dur":4,"text":"Before that, we had two separate\nmesocyclones with--"},"1418":{"dur":3,"text":"it looked to be a cone tornado,\nand then off to our"},"1421":{"dur":2,"text":"east probably a quarter to a\nhalf mile was a stovepipe"},"1424":{"dur":3,"text":"tornado, a lot of power\nflashes with it."},"1427":{"dur":1,"text":"-All right, Darren."},"1428":{"dur":0,"text":"And I know you've--"},"1429":{"dur":0,"text":"PROFESSOR: I'm going to stop"},"1430":{"dur":2,"text":"that there for a minute."},"1433":{"dur":2,"text":"Well, I guess I'll stop\nit there anyway."},"1435":{"dur":2,"text":"But there are two things I\nwanted to point out to you."},"1437":{"dur":1,"text":"So he's got two things\nhe's looking at."},"1439":{"dur":4,"text":"He's got the radar, and he's\nlooking at the reflectivity,"},"1444":{"dur":2,"text":"which is telling you where\nthe rain is falling."},"1446":{"dur":4,"text":"And in that, he's finding\nthis shape, which is"},"1451":{"dur":1,"text":"called the hook echo."},"1455":{"dur":2,"text":"So there's rain falling through\nhere, and the spin up"},"1458":{"dur":4,"text":"in the cloud is wrapping\nthis rain shaft around"},"1463":{"dur":2,"text":"in a kind of spiral."},"1465":{"dur":2,"text":"And that's a very clear\nsignature of a very strong"},"1468":{"dur":2,"text":"cyclone aloft."},"1470":{"dur":1,"text":"Then he's also got\nthe Doppler."},"1471":{"dur":6,"text":"For the same instrument, the\nsame radar, it measures the"},"1477":{"dur":3,"text":"frequency of the reflected\nradar beam."},"1481":{"dur":2,"text":"And they know what frequency\nthey sent out."},"1484":{"dur":3,"text":"If it comes back a higher\nfrequency, that means the air"},"1487":{"dur":2,"text":"at that location is moving\ntowards you."},"1489":{"dur":1,"text":"If it comes back at a lower\nfrequency, it's"},"1491":{"dur":0,"text":"moving away from you."},"1492":{"dur":2,"text":"This is the Doppler effect."},"1494":{"dur":3,"text":"When a car goes by or a train\ngoes by, you hear that"},"1498":{"dur":1,"text":"[ZOOMING NOISE]"},"1499":{"dur":2,"text":"as it's coming towards you and\nthen going away from you."},"1502":{"dur":1,"text":"There's that frequency shift."},"1503":{"dur":3,"text":"And what he was showing with\nthese two regions, one was red"},"1507":{"dur":4,"text":"and one was blue, indicating in\none region the wind is away"},"1511":{"dur":2,"text":"from you, in the other region\nit's toward you."},"1514":{"dur":5,"text":"So it probably was like this\nif the radar was down here,"},"1519":{"dur":3,"text":"which means there\nis a cyclone."},"1523":{"dur":0,"text":"On this side its--you're not"},"1524":{"dur":1,"text":"measuring this other component."},"1525":{"dur":1,"text":"You're just measuring the\ncomponent towards and away"},"1527":{"dur":0,"text":"from the radar."},"1528":{"dur":5,"text":"But when you see that doublet,\nthat velocity away from you"},"1533":{"dur":3,"text":"and velocity towards you,\nthere's really only one"},"1536":{"dur":0,"text":"explanation for that."},"1537":{"dur":3,"text":"There's a tight vortex right in\nthere up in the cloud, and"},"1540":{"dur":4,"text":"very possibly that's causing\na tornado at the ground."},"1545":{"dur":3,"text":"So what's nice about that\nfilm loop is that's"},"1549":{"dur":1,"text":"not after the fact."},"1550":{"dur":1,"text":"That's during the fact."},"1551":{"dur":3,"text":"So he's putting himself on the\nline and saying, listen, I"},"1554":{"dur":3,"text":"know sometimes we have false\nalarms about these things, but"},"1558":{"dur":3,"text":"this is one of the strongest\nsignatures I've ever seen."},"1561":{"dur":4,"text":"So he's putting out that kind\nof warning to the people."},"1566":{"dur":2,"text":"It's pretty-- it takes some\nguts to do that, because"},"1568":{"dur":3,"text":"occasionally they do\nget this wrong."},"1572":{"dur":4,"text":"So we're going to continue,\nand I think that's--"},"1577":{"dur":3,"text":"yeah, so that's all we have on\nsevere thunderstorms. Are"},"1580":{"dur":7,"text":"there any questions on severe\nthunderstorms before we go on"},"1587":{"dur":1,"text":"to another subject?"},"1592":{"dur":2,"text":"So you can read about\nit in this book."},"1595":{"dur":1,"text":"It's fascinating stuff."},"1597":{"dur":2,"text":"And we'll turn to hurricanes."},"1602":{"dur":3,"text":"Now, a few basic bullet points\nabout hurricanes."},"1605":{"dur":3,"text":"As with other convective storms,\nthey get their energy"},"1608":{"dur":2,"text":"from latent heat release."},"1611":{"dur":3,"text":"In this case, they get\nthat water vapor"},"1614":{"dur":2,"text":"directly from the ocean."},"1617":{"dur":6,"text":"So it doesn't-- you don't use\nup the water vapor in the"},"1623":{"dur":5,"text":"atmosphere as a tornado begins\nto draw on it, because with a"},"1629":{"dur":3,"text":"warm ocean, you can evaporate\nwater from the ocean just as"},"1633":{"dur":2,"text":"fast as you're drawing\nit up in the storm."},"1635":{"dur":3,"text":"So in one way, it's better to\nsay that really it's the warm"},"1639":{"dur":5,"text":"ocean that provides the fuel\nfor this, but yet it's also"},"1644":{"dur":0,"text":"water vapor."},"1645":{"dur":4,"text":"The warm water evaporates, and\nthen you get the water vapor"},"1649":{"dur":1,"text":"that goes up into the cloud."},"1650":{"dur":3,"text":"And as it rises, you get the\nlatent heat release and the"},"1654":{"dur":2,"text":"buoyancy and so on\nand so forth."},"1656":{"dur":3,"text":"Now, if you have too\nmuch wind shear--"},"1659":{"dur":3,"text":"this is just the opposite of\nthe severe thunderstorm."},"1663":{"dur":3,"text":"Severe thunderstorms require\nthat wind shear to distort it"},"1666":{"dur":3,"text":"and give it that severe\ncondition, whereas hurricanes"},"1670":{"dur":2,"text":"out over the ocean, if you have\na lot of wind shear, they"},"1673":{"dur":1,"text":"will not form."},"1674":{"dur":4,"text":"They're a symmetric kind of\ndeal, and if you try to shear"},"1678":{"dur":1,"text":"that off, you'll just\ndestroy it."},"1680":{"dur":3,"text":"So you need a lot of warm ocean\nwater and not very much"},"1684":{"dur":4,"text":"shear, and then you can, under\nsome conditions, you can"},"1688":{"dur":2,"text":"generate a hurricane."},"1690":{"dur":2,"text":"They cannot form at the Equator,\nbecause they have to"},"1692":{"dur":4,"text":"spin one way or the other, and\nthey get that cue from the"},"1697":{"dur":1,"text":"Coriolis force."},"1698":{"dur":2,"text":"And so if there's no\nCoriolis force, you"},"1700":{"dur":2,"text":"cannot form a hurricane."},"1703":{"dur":1,"text":"So they cannot form\nat the Equator."},"1704":{"dur":2,"text":"And as I mentioned the other\nday, they cannot even cross"},"1707":{"dur":1,"text":"the Equator."},"1708":{"dur":2,"text":"Once they've formed in one\nhemisphere, they've got to"},"1710":{"dur":0,"text":"stay in that hemisphere."},"1711":{"dur":3,"text":"They can't suddenly decide to\nwander across to the other"},"1714":{"dur":5,"text":"They couldn't exist with the\nspin that they have. They do"},"1719":{"dur":3,"text":"spin oppositely in the\ntwo hemispheres."},"1723":{"dur":3,"text":"Just like in the tornado, the\npressure is very low in the"},"1726":{"dur":4,"text":"center, and that balances the\nCoriolis force and the"},"1731":{"dur":3,"text":"centripetal force of the air\nspinning around the outside."},"1734":{"dur":3,"text":"So this is a cyclone in the\nsame sense that I defined"},"1738":{"dur":2,"text":"cyclone for you the other day."},"1740":{"dur":4,"text":"It's a low-pressure center\nwith air currents moving"},"1745":{"dur":2,"text":"around it in a cyclonic\ndirection--"},"1747":{"dur":2,"text":"that is, counterclockwise in\nthe Northern Hemisphere,"},"1749":{"dur":3,"text":"clockwise in the Southern\nHemisphere."},"1753":{"dur":2,"text":"They occur in the late summer\nand early fall in both"},"1755":{"dur":1,"text":"hemispheres."},"1757":{"dur":7,"text":"Be careful how you use those\nterms. On land, the highest"},"1764":{"dur":4,"text":"temperatures normally occur four\nto six weeks after the"},"1769":{"dur":1,"text":"summer solstice."},"1771":{"dur":3,"text":"The summer solstice\nis about June 21."},"1774":{"dur":5,"text":"The warmest days of summer are\nusually mid-July for air over"},"1780":{"dur":1,"text":"the continents."},"1781":{"dur":3,"text":"But oceans have more heat\ncapacity, and they take a"},"1785":{"dur":2,"text":"longer time to warm up."},"1787":{"dur":3,"text":"So the warmer ocean temperatures\noccur almost"},"1791":{"dur":4,"text":"three months after the\nsummer solstice."},"1795":{"dur":3,"text":"The warmest ocean temperatures\ntypically are in August,"},"1798":{"dur":1,"text":"September, and October."},"1800":{"dur":4,"text":"And since the hurricanes need\nthat, they need warm ocean"},"1804":{"dur":5,"text":"temperatures, the hurricane\nseason is then delayed that"},"1809":{"dur":0,"text":"three months."},"1810":{"dur":2,"text":"So it's not midsummer\nor early summer."},"1812":{"dur":2,"text":"It's late summer and early fall,\nbecause that's when the"},"1815":{"dur":1,"text":"ocean's sea surface\ntemperature--"},"1816":{"dur":4,"text":"SST is the abbreviation for\nsea surface temperature--"},"1820":{"dur":3,"text":"is the highest. That\ndefines the"},"1824":{"dur":1,"text":"so-called hurricane season."},"1825":{"dur":2,"text":"Now remember, in the Northern\nHemisphere, that is going to"},"1828":{"dur":5,"text":"be July, August, September,\nand maybe a little bit in"},"1833":{"dur":5,"text":"October, whereas in the Southern\nHemisphere, that is"},"1839":{"dur":4,"text":"going to be, well, January,\nFebruary, March, and April in"},"1843":{"dur":1,"text":"the Southern Hemisphere."},"1845":{"dur":2,"text":"That's their summertime, and\nthat's when hurricanes are"},"1847":{"dur":4,"text":"going to be most frequent in\nthe Southern Hemisphere."},"1852":{"dur":3,"text":"They tend to drift westward,\nbecause they occur in the"},"1856":{"dur":5,"text":"tropics under the influence\nof the trade winds."},"1861":{"dur":3,"text":"It's like you had a stream of\nwater and you dip your hand in"},"1864":{"dur":2,"text":"and made a little vortex, and\nyou would watch and see that"},"1867":{"dur":3,"text":"that vortex is just carried\nalong by the stream."},"1870":{"dur":2,"text":"Whatever direction the stream is\ngoing in, that vortex would"},"1873":{"dur":0,"text":"move as well."},"1874":{"dur":6,"text":"And that's primarily what's\ngoing on when tornado is--"},"1880":{"dur":1,"text":"when a hurricane is\nmoving westward."},"1882":{"dur":3,"text":"However, it also has a poleward\ndrift that can't be"},"1886":{"dur":3,"text":"explained as simply as that, and\nthat has something to do"},"1889":{"dur":1,"text":"with the curvature\nof the Earth."},"1891":{"dur":1,"text":"I've published on this,\nbut I don't have time"},"1893":{"dur":6,"text":"But there is a drift of\nhurricanes toward the pole in"},"1900":{"dur":1,"text":"both hemispheres--"},"1902":{"dur":2,"text":"the North Pole in the Northern\nHemisphere, the South Pole in"},"1904":{"dur":1,"text":"the Southern Hemisphere--"},"1906":{"dur":4,"text":"that is added to that general\nwestward drift due to being in"},"1911":{"dur":1,"text":"the belt of the easterly\ntrade winds."},"1916":{"dur":5,"text":"So these are the global\nhurricane tracks."},"1921":{"dur":3,"text":"It's interesting for what is in\nthis diagram and what's not"},"1924":{"dur":0,"text":"in this diagram."},"1925":{"dur":3,"text":"For example, in the North\nAtlantic Ocean--"},"1929":{"dur":3,"text":"the Equator is about here--"},"1932":{"dur":4,"text":"generally, hurricanes form in\nthe central and sometimes even"},"1936":{"dur":4,"text":"eastern part of the tropical\nNorth Atlantic, and then they"},"1940":{"dur":1,"text":"move westward and northward."},"1942":{"dur":3,"text":"So generally, they follow a\nlooping trajectory like this,"},"1946":{"dur":3,"text":"or maybe they go straight into\nthe Gulf of Mexico or through"},"1949":{"dur":4,"text":"the Caribbean into the Gulf\nof Mexico like that."},"1954":{"dur":6,"text":"In the eastern tropical North\nPacific, you have a very high"},"1961":{"dur":3,"text":"density of hurricanes."},"1964":{"dur":3,"text":"Most of these don't threaten\nland, because they're going"},"1967":{"dur":3,"text":"out to sea, but some of them\nthat move up along the coast"},"1971":{"dur":2,"text":"can threaten land."},"1973":{"dur":2,"text":"They don't go very far north,\nbecause there's a cold"},"1975":{"dur":4,"text":"California Current that\ncomes down here."},"1979":{"dur":1,"text":"I didn't put this in the notes,\nbut you should write it"},"1981":{"dur":3,"text":"down that many people think\nthere's a critical ocean"},"1984":{"dur":3,"text":"temperature below which you\ncannot have hurricanes."},"1988":{"dur":3,"text":"And some people will tell you\nthat's 27 degrees Celsius."},"1991":{"dur":2,"text":"Some people say it's\n28 degrees Celsius."},"1994":{"dur":3,"text":"But somewhere about there is a\ncritical ocean temperature."},"1998":{"dur":2,"text":"And so the ocean has to be\nwarmer than, let's say, 28"},"2001":{"dur":4,"text":"Celsius before it can\nsupport a hurricane."},"2005":{"dur":3,"text":"And you don't have that up\nhere, because the cold"},"2008":{"dur":2,"text":"California Current comes\ndown, but closer to"},"2011":{"dur":1,"text":"the Equator you do."},"2012":{"dur":3,"text":"Notice, right at the Equator,\nno hurricanes."},"2015":{"dur":4,"text":"Plenty of warm water, but\nno Coriolis force, so no"},"2020":{"dur":2,"text":"hurricanes."},"2022":{"dur":5,"text":"The western tropical North\nPacific is a hotbed-- the"},"2028":{"dur":4,"text":"world's biggest hotbed\nof hurricanes."},"2032":{"dur":2,"text":"Be careful, though."},"2034":{"dur":4,"text":"The word \"hurricane\"\ntraditionally is not used in"},"2038":{"dur":1,"text":"that part of the world."},"2040":{"dur":4,"text":"These are normally referred to\nas typhoons, after a Japanese"},"2044":{"dur":4,"text":"word for \"hurricane.\" So it\nwouldn't be wrong to call"},"2049":{"dur":3,"text":"these hurricanes, but it\nwouldn't be the vernacular."},"2052":{"dur":2,"text":"The vernacular would\nbe typhoon."},"2055":{"dur":4,"text":"And so if I say there's a\ntyphoon in the Western"},"2059":{"dur":1,"text":"Pacific, you'll know\nI'm talking"},"2060":{"dur":1,"text":"about a hurricane there."},"2062":{"dur":2,"text":"And they've got the same kind of\npattern as in the Atlantic."},"2065":{"dur":3,"text":"They go westward, but they\nalso arc northwards."},"2069":{"dur":3,"text":"In the Indian Ocean, you get\nsome in the Arabian Sea and"},"2073":{"dur":2,"text":"the Bay of Bengal."},"2075":{"dur":2,"text":"Not many, but you do\nget some, and they"},"2077":{"dur":1,"text":"can be quite damaging."},"2078":{"dur":1,"text":"In the Southern Hemisphere,\nlook at this."},"2080":{"dur":1,"text":"You get them in the\nIndian Ocean."},"2081":{"dur":2,"text":"You get them in the west\ntropical Pacific."},"2084":{"dur":5,"text":"You don't get them in\nthe east at all."},"2089":{"dur":6,"text":"And I would've said you don't\nget them in the Atlantic, but"},"2095":{"dur":1,"text":"there was one about\nfour years ago."},"2097":{"dur":4,"text":"It was the first-ever reported\nhurricane in the tropical"},"2101":{"dur":2,"text":"South Pacific, and they've got\nthat one marked in here."},"2104":{"dur":1,"text":"Now, this is pretty\neasy to explain."},"2106":{"dur":1,"text":"There's a cold current--"},"2108":{"dur":2,"text":"it's called the Humboldt\nCurrent,"},"2110":{"dur":2,"text":"after a German explorer--"},"2112":{"dur":2,"text":"a cold current that comes up\nalong the coast of South"},"2114":{"dur":7,"text":"America and floods this part\nof the southern eastward"},"2122":{"dur":1,"text":"tropical Pacific."},"2124":{"dur":1,"text":"And therefore, the temperatures\nare not warm"},"2125":{"dur":2,"text":"enough to support hurricanes."},"2127":{"dur":2,"text":"And pretty much the same\nthing is true here."},"2130":{"dur":3,"text":"There's a cold current that\ncomes up along here."},"2133":{"dur":3,"text":"And while there is some warm air\nright-- some water right"},"2137":{"dur":3,"text":"along the Equator, there you\ndon't have the Coriolis force."},"2141":{"dur":2,"text":"And here you've got the Coriolis\nforce, but the"},"2143":{"dur":1,"text":"temperatures are too low."},"2144":{"dur":3,"text":"So you're not getting those two\ningredients together, the"},"2147":{"dur":3,"text":"warm water and the\nCoriolis force."},"2151":{"dur":2,"text":"Questions on this diagram?"},"2154":{"dur":3,"text":"Remember, these are not\noccurring simultaneously."},"2158":{"dur":3,"text":"This is in Northern Hemisphere\nhurricane season."},"2161":{"dur":2,"text":"These are in Southern Hemisphere\nhurricane season."},"2164":{"dur":5,"text":"We've just put them all together\non one diagram there."},"2169":{"dur":6,"text":"So here's a zoom in of\nthe Atlantic Ocean."},"2175":{"dur":3,"text":"And you can see that\nmany of them come--"},"2179":{"dur":3,"text":"so once a hurricane gets\nstarted, it's going to"},"2182":{"dur":4,"text":"persist. It's a good,\nstable storm system."},"2186":{"dur":1,"text":"It'll persist until\nthe conditions no"},"2188":{"dur":2,"text":"longer make it possible."},"2191":{"dur":2,"text":"One of two things will happen."},"2194":{"dur":3,"text":"It'll move over land, in which\ncase it no longer has that"},"2197":{"dur":4,"text":"water supply, or it'll move over\ncold water, in which case"},"2202":{"dur":2,"text":"it no longer has enough\nwater supply."},"2204":{"dur":5,"text":"Because the water can't\nevaporate fast enough from a"},"2209":{"dur":1,"text":"cold ocean."},"2213":{"dur":3,"text":"Typically, from the satellite,\nthey look like this."},"2217":{"dur":3,"text":"They have a well-developed,\nlarge cloud shield."},"2221":{"dur":3,"text":"It's like a thunderstorm anvil,\nexcept it's kind of"},"2224":{"dur":0,"text":"axisymmetric."},"2225":{"dur":4,"text":"That means moving out\nin all directions."},"2229":{"dur":3,"text":"And very often, but not always,\nthere's an eye, which"},"2233":{"dur":2,"text":"is a very peculiar\ncharacteristic."},"2236":{"dur":4,"text":"The air everywhere else is\nrising, but right there, the"},"2240":{"dur":1,"text":"air is sinking."},"2241":{"dur":2,"text":"I know that because it's\nclear of clouds."},"2244":{"dur":4,"text":"Clear of clouds means sinking\nair, thermodynamically."},"2248":{"dur":6,"text":"Underneath this, you can't see\nit, but the winds are strong"},"2254":{"dur":2,"text":"in the cyclonic direction."},"2257":{"dur":4,"text":"So here's kind of a cartoonish\ncross-section."},"2261":{"dur":2,"text":"You've got these rain bands."},"2264":{"dur":3,"text":"The rain is not uniform in a\nhurricane but forms in these"},"2267":{"dur":3,"text":"spiral, heavy-raining bands."},"2271":{"dur":3,"text":"The air rises in this main\neyewall and then spreads out"},"2274":{"dur":1,"text":"in this giant anvil."},"2276":{"dur":2,"text":"First, it's still moving in\nthe cyclonic direction."},"2279":{"dur":2,"text":"When that air moves far enough\nout, the Coriolis force acts"},"2282":{"dur":3,"text":"on it and actually reverses\nits sense of direction."},"2285":{"dur":0,"text":"So be careful."},"2286":{"dur":3,"text":"If you're looking at movies of\nhurricanes, you may find that"},"2289":{"dur":4,"text":"the outer clouds are actually\nmoving anticyclonically."},"2294":{"dur":1,"text":"Don't be confused."},"2295":{"dur":4,"text":"All the rest of the storm is\nstill a tight, cyclonically"},"2300":{"dur":2,"text":"spinning vortex."},"2302":{"dur":3,"text":"And then a little bit of that\nair that rises in the eyewall"},"2306":{"dur":4,"text":"sinks right down in the eye and\nkeeps that little section"},"2310":{"dur":1,"text":"clear of clouds."},"2312":{"dur":3,"text":"Most of it, however, spreads out\nin this giant anvil, whose"},"2316":{"dur":4,"text":"diameter is several hundred\nkilometers across."},"2321":{"dur":2,"text":"So hurricane damage, of\ncourse, wind impact on"},"2324":{"dur":1,"text":"buildings and vegetation."},"2325":{"dur":3,"text":"Remember that the pressure\nthat a wind exerts on a"},"2328":{"dur":5,"text":"surface is proportional to the\nsquare of the wind speed."},"2333":{"dur":3,"text":"So if you have a 10 meter per\nsecond wind hitting my house,"},"2337":{"dur":1,"text":"that produces a certain force."},"2339":{"dur":3,"text":"If you have a 20 meters per\nsecond, that's four times--"},"2342":{"dur":3,"text":"twice the speed, but four\ntimes the pressure force"},"2346":{"dur":1,"text":"pushing on the house,\nand so on."},"2348":{"dur":4,"text":"So if you have a hurricane\nthat's 60 meters per second or"},"2352":{"dur":5,"text":"120 meters per second, the\ndestructive forces of that"},"2357":{"dur":6,"text":"push really go up very, very\nsteeply and can destroy most"},"2364":{"dur":2,"text":"buildings, unless they're\nspecially designed to be"},"2367":{"dur":2,"text":"hurricane-secure."},"2369":{"dur":2,"text":"Another thing is that\nstorm surge."},"2372":{"dur":4,"text":"The rapid air movement across\nthe surface of the ocean"},"2377":{"dur":4,"text":"pushes water towards the shore\nand will give an apparent rise"},"2381":{"dur":0,"text":"in sea level."},"2382":{"dur":3,"text":"We talked about this when we\nwere discussing Irene."},"2385":{"dur":3,"text":"And if you're standing on the\nbeach, the water just suddenly"},"2388":{"dur":2,"text":"seems to rise and move inland."},"2391":{"dur":2,"text":"On top of that, there's going to\nbe the waves caused by the"},"2393":{"dur":3,"text":"winds as well, but that storm\nsurge is often responsible for"},"2397":{"dur":2,"text":"some of the major damage."},"2399":{"dur":2,"text":"Inland flooding as well, and\nwe saw that in Irene."},"2402":{"dur":3,"text":"Poor Vermont, and New Jersey to\nsome extent too, had a lot"},"2405":{"dur":3,"text":"of rainfall, which collected\nquickly into the valleys and"},"2409":{"dur":3,"text":"rivers and caused a\nlot of flooding."},"2412":{"dur":4,"text":"Of course, for many people here\nin Connecticut, the main"},"2416":{"dur":2,"text":"impact of Hurricane Irene\nwas losing their"},"2419":{"dur":2,"text":"electrical power for days."},"2421":{"dur":4,"text":"And that's mostly in this part\nof the world, because the wind"},"2426":{"dur":3,"text":"will take down a tree limb and\nwipe out most-- in this"},"2430":{"dur":4,"text":"country, most of our power\nlines are above ground."},"2434":{"dur":4,"text":"It's cheaper to do that, easy to\nmaintain in most cases, but"},"2438":{"dur":3,"text":"they're so vulnerable\nto tipping trees."},"2441":{"dur":2,"text":"So when you got a high wind\nevent like this, trees come"},"2444":{"dur":2,"text":"down, hit the wires."},"2446":{"dur":2,"text":"You lose both communication\nand power."},"2449":{"dur":6,"text":"In other parts of the world,\nhurricanes are often followed"},"2455":{"dur":5,"text":"a few weeks later by enormous\nloss of life from disease."},"2460":{"dur":3,"text":"For example, if you have a\nhurricane hitting Bangladesh"},"2463":{"dur":4,"text":"or some of the other undeveloped\ncountries, what"},"2467":{"dur":1,"text":"you'll have--"},"2469":{"dur":2,"text":"the hurricane will be finished\nand it'll be"},"2471":{"dur":2,"text":"long gone, and then--"},"2473":{"dur":2,"text":"but people will be displaced\nfrom their homes."},"2475":{"dur":2,"text":"And more importantly, water\nsources get mixed."},"2478":{"dur":3,"text":"So sewage gets into drinking\nwater typically, and then"},"2482":{"dur":1,"text":"disease begins."},"2483":{"dur":2,"text":"And in the weeks and months that\nfollow, you could have"},"2486":{"dur":4,"text":"hundreds, thousands, even tens\nof thousands of deaths arising"},"2490":{"dur":4,"text":"from the, quote, \"hurricane,\"\nbut it really has to do with"},"2494":{"dur":3,"text":"just contamination of water\nsupplies and a lack of a"},"2498":{"dur":3,"text":"public health service to be sure\nthat that sort of thing"},"2501":{"dur":0,"text":"doesn't happen."},"2502":{"dur":4,"text":"So this is the biggest loss of\nlife from hurricanes by far,"},"2506":{"dur":4,"text":"but these other things are\nimportant as well."},"2511":{"dur":3,"text":"Any questions on that?"},"2514":{"dur":5,"text":"So the most famous hurricane in\nNew England was nicknamed"},"2519":{"dur":3,"text":"the Long Island Express\nin 1938."},"2523":{"dur":5,"text":"It had a track like this and\nhit Connecticut directly."},"2528":{"dur":2,"text":"A lot of damage along the\nConnecticut coast, even more"},"2531":{"dur":4,"text":"along the Rhode Island coast.\nThe hurricane produces its"},"2535":{"dur":2,"text":"biggest damage on the right\nfront quadrant."},"2538":{"dur":3,"text":"So it's got four quadrants\nbased on how it's moving."},"2541":{"dur":4,"text":"It's that right front quadrant\nthat tends to have the"},"2545":{"dur":2,"text":"strongest winds and in many\ncases the heaviest"},"2547":{"dur":1,"text":"precipitation."},"2548":{"dur":3,"text":"And in this case, that hit Rhode\nIsland and caused a lot"},"2552":{"dur":1,"text":"of damage there."},"2553":{"dur":3,"text":"If you Google \"hurricane, 1938,\"\nthat one will pop up,"},"2557":{"dur":1,"text":"and you can read all about it."},"2559":{"dur":2,"text":"It really was a major event\nand is still talked about"},"2561":{"dur":1,"text":"today in Connecticut."},"2563":{"dur":2,"text":"We had our own chance at this\njust a few weeks ago."},"2565":{"dur":4,"text":"Hurricane Irene had a track\nsimilar to that but not"},"2569":{"dur":1,"text":"exactly the same."},"2570":{"dur":3,"text":"The difference probably was that\nit brushed ashore here"},"2574":{"dur":5,"text":"near Cape Hatteras and lost a\nlot of its strength before it"},"2579":{"dur":4,"text":"hit New England, partly by its\nlack of water vapor over the"},"2583":{"dur":2,"text":"land and also the frictional--"},"2585":{"dur":3,"text":"with all the trees and so on\nover land, that friction"},"2589":{"dur":4,"text":"So by the time it hit us, it had\nweakened to a Category 2"},"2594":{"dur":2,"text":"or perhaps even 1."},"2597":{"dur":4,"text":"And it still caused a lot of\nflooding damage but not so"},"2602":{"dur":4,"text":"much wind damage and\nother things."},"2606":{"dur":2,"text":"And then of course, the most\ndamaging hurricane in our"},"2609":{"dur":3,"text":"country's history was\nHurricane Katrina"},"2612":{"dur":2,"text":"in August of 2005."},"2614":{"dur":1,"text":"And it had a different track."},"2615":{"dur":2,"text":"It started here in\nthe eastern--"},"2617":{"dur":3,"text":"well, just north of Cuba,\ncrossed over the southern tip"},"2621":{"dur":3,"text":"of Florida, regained\nits strength, and"},"2625":{"dur":3,"text":"then hit New Orleans."},"2628":{"dur":4,"text":"And you can read all about\nthat in the history books"},"2632":{"dur":0,"text":"now-- in history\nbooks now too."},"2633":{"dur":3,"text":"And there's a picture of Katrina\njust as it was about"},"2636":{"dur":5,"text":"to hit New Orleans, a\nbeautifully formed storm with"},"2641":{"dur":4,"text":"a beautiful central eye\nand the cloud shield"},"2645":{"dur":1,"text":"and the whole business."},"2647":{"dur":8,"text":"Very strong storm that\nhit New Orleans."},"2655":{"dur":2,"text":"This is what I mentioned\nbefore."},"2657":{"dur":3,"text":"There's a well-defined\nhurricane season."},"2661":{"dur":4,"text":"And here it is for Atlantic\nhurricanes."},"2665":{"dur":2,"text":"And of course, when I say\n\"Atlantic,\" I'm referring to"},"2668":{"dur":0,"text":"North Atlantic."},"2669":{"dur":1,"text":"Because, remember, there are\nno hurricanes in the South"},"2670":{"dur":3,"text":"Atlantic, so this is the\nNorthern Hemisphere hurricane"},"2674":{"dur":2,"text":"frequencies for the\nAtlantic Ocean."},"2676":{"dur":4,"text":"And typically, the frequency\nis non-negligible even in"},"2681":{"dur":3,"text":"June, but it begins to rise\nquickly at the first of"},"2684":{"dur":4,"text":"August, peaks in early,\nmid-September, and then you're"},"2688":{"dur":3,"text":"kind of out of the woods by\nthe time you get to the"},"2692":{"dur":2,"text":"beginning or the middle\nof November."},"2695":{"dur":6,"text":"And this all has to do with\nocean surface temperatures."},"2701":{"dur":1,"text":"Questions on that?"},"2708":{"dur":0,"text":"Yes."},"2709":{"dur":4,"text":"Well, it is-- we have five\nminutes to go, but rather than"},"2713":{"dur":3,"text":"starting a new subject, why\ndon't we call it quits today?"},"2716":{"dur":4,"text":"And we'll do mid-latitude\nfrontal cyclones on Friday."}}