{"5.95":{"start":"5.95","dur":"1.62","text":"We&#39;re going to talk about"},"7.57":{"start":"7.57","dur":"1.32","text":"Adelbert Ames today"},"8.89":{"start":"8.89","dur":"9.44","text":"and this is my title slide so. I was\ntrying to put words on it and either I"},"18.33":{"start":"18.33","dur":"3.13","text":"could tattoo it on his forehead"},"21.46":{"start":"21.46","dur":"5.34","text":"or I could blend it in his collar. so you\ndon&#39;t get any words but that&#39;s the title"},"26.80":{"start":"26.8","dur":"5.29","text":"slide and that is Adelbert Ames. to cut\noff this question which I&#39;ve had a"},"32.09":{"start":"32.09","dur":"4.2","text":"couple of times already. It&#39;s Ad-DEL-bert\nand I don&#39;t know  if you&#39;re like me"},"36.29":{"start":"36.29","dur":"6.229","text":"but I always said ADD-el-bert. If I don&#39;t watch\nmyself I&#39;ll say it again because ADD-el-bert, I I"},"42.52":{"start":"42.519","dur":"4.25","text":"don&#39;t know it just looks like ADD-el-bert to southerners but it&#39;s ad-DEL-bert."},"46.77":{"start":"46.769","dur":"6.171","text":"we&#39;re gonna be talking about Ames and\nit&#39;s not really I don&#39;t think I&#39;m"},"52.94":{"start":"52.94","dur":"5.799","text":"surprising anybody but it&#39;s not really a\nmilitary study. I&#39;ll gloss over everything"},"58.74":{"start":"58.739","dur":"3","text":"thats going out there."},"62.33":{"start":"62.329","dur":"4.07","text":"I feel like - you remember  those old\ntruck stop motels we could put a quarter"},"66.40":{"start":"66.399","dur":"3","text":"in the bed? [Crowd laughter]"},"74.17":{"start":"74.17","dur":"27.129","text":"So it&#39;s not a military study. basically the\nyears from 1865 to 1875 is what we will be"},"101.30":{"start":"101.299","dur":"8.011","text":"focusing on.1876. and to show you what\nthey did in the post-war years and of"},"109.31":{"start":"109.31","dur":"5.949","text":"course to link it to my home state of\nMississippi which obviously has a key"},"115.26":{"start":"115.259","dur":"1.29","text":"connection with me. I&#39;m"},"116.55":{"start":"116.549","dur":"5.981","text":"interested in the subject and I needed\nsomething on Reconstruction. now to begin with"},"122.53":{"start":"122.53","dur":"6.239","text":"Adelbert is born in Rockland Maine in\nOctober of 1835. well you do the math on"},"128.77":{"start":"128.769","dur":"6.03","text":"that -  how old he&#39;s \ngoing to be when the Civil War breaks out."},"134.80":{"start":"134.799","dur":"4.401","text":"his youth was spent surrounded by\nstories of the founding fathers and"},"139.20":{"start":"139.2","dur":"6.77","text":"debates on politics and his father, if you\ncould get a better father or a better"},"145.97":{"start":"145.97","dur":"4.769","text":"living for a father was a merchant captain\nand his father circumvented the globe"},"150.74":{"start":"150.739","dur":"3.551","text":"numerous times. before his father&#39;s death"},"154.29":{"start":"154.29","dur":"3.8","text":"Adelbert accompanied is his dad on\nseveral occasions visiting various"},"158.09":{"start":"158.09","dur":"5.739","text":"foreign ports and furthering his\nstudies in the meantime. the one thing"},"163.83":{"start":"163.829","dur":"4.78","text":"that I get about Adlebert Ames as I go\nthrough his bio right here is he&#39;s"},"168.61":{"start":"168.609","dur":"6.281","text":"refined.He&#39;s classy.  he&#39;s a you know he&#39;s a\nhe&#39;s a gentleman in the first sense of the"},"174.89":{"start":"174.89","dur":"5.98","text":"word. really educated. in 1855 Ames is\ngoing to enter West Point Military"},"180.87":{"start":"180.87","dur":"8.08","text":"Academy and the superintendent at that\ntime was an officer by the name of Robert"},"188.95":{"start":"188.95","dur":"7.24","text":"E Lee. Ames did well at West Point he\nwould. he&#39;s well-prepared for it."},"196.19":{"start":"196.19","dur":"3.04","text":"He went through five years of training at the\nPoint."},"199.23":{"start":"199.23","dur":"4.7","text":"one of my coworkers was asking me why he\ndid five years at the Point. now I don&#39;t"},"203.93":{"start":"203.93","dur":"5.44","text":"really have an answer for that."},"213.69":{"start":"213.69","dur":"13.66","text":"By the second yearof his five years he stood forth in his\nclass. by his fifth year he stood fifth"},"227.35":{"start":"227.35","dur":"6.9","text":"out of a class of forty five in\ngeneral merit -  overall category. Ames"},"234.25":{"start":"234.25","dur":"5.43","text":"stood at roughly six feet in height, his \nhair was dark brown, his eyes hazel brown - much"},"239.68":{"start":"239.68","dur":"8.08","text":"which like some people&#39;s spouses. now with\nwar impending Ames was assigned to the"},"247.76":{"start":"247.76","dur":"4.63","text":"5th US Artillery  known as the West\nPoint Light Artillery. it was commanded"},"252.39":{"start":"252.39","dur":"6.42","text":"by Ames&#39; friend Charles Griffin. now action\ncame soon enough in the First Battle of"},"258.81":{"start":"258.81","dur":"5.5","text":"Bull Run July of 1861. Ames found his\nbattery getting  all the adventure"},"264.31":{"start":"264.31","dur":"4.4","text":"they wanted on top of Henry Hill which\nis the main portion of the battlefield."},"268.71":{"start":"268.71","dur":"5.98","text":"in the midst of the fighting Ames is\ngonna receive a wound in the thigh and"},"274.69":{"start":"274.69","dur":"5.57","text":"he will refuse to relinquish\nthe field his soldiers will take him and"},"280.26":{"start":"280.26","dur":"5.37","text":"prop him up on a limber or a caisson and he\nwill continue to direct the fire of the"},"285.63":{"start":"285.63","dur":"7.62","text":"battery from that limber right there. can\nyou imagine? Ames stayed so long that the"},"293.25":{"start":"293.25","dur":"7.11","text":"loss of blood eventually made him faint. I&#39;m sure\nthat was hard to tie off - a thigh wound.  he would"},"300.36":{"start":"300.36","dur":"6.35","text":"posthumously, after the war, won the\nMedal of Honor for this action. so later"},"306.71":{"start":"306.71","dur":"6.19","text":"on in this slide program when you think\nyou see an MOH on him  that is one."},"312.90":{"start":"312.9","dur":"5.11","text":"Now Ames returned from his wound in time to\nserve during the Seven Days battle, that&#39;s"},"318.01":{"start":"318.01","dur":"5.52","text":"around Richmond, and he was breveted to\nlieutenant colonel of volunteers for"},"323.53":{"start":"323.53","dur":"4.29","text":"gallantry at Malvern Hill. Ames wanted\nhigher rank though and after"},"327.82":{"start":"327.82","dur":"5.4","text":"politicking in Maine for a slot, he\nreceived command the 20th Maine in"},"333.22":{"start":"333.22","dur":"6.75","text":"August of 1862. as commander of the\n20th Maine he was at Antietam"},"339.97":{"start":"339.97","dur":"4.63","text":"but luckily his group his regiment did\nnot see much action during the battle."},"344.60":{"start":"344.6","dur":"1.89","text":"although Chamberlain"},"346.49":{"start":"346.49","dur":"6.769","text":"gets all the attention it was actually\nAmes who led the 20th Maine during one"},"353.26":{"start":"353.259","dur":"5.081","text":"of the charges at Fredericksburg. was that\nGods and Generals where they cover Fredericksburg?"},"358.34":{"start":"358.34","dur":"6.69","text":"After Fredericksburg Ames\nwent on a temporary detail to the staff"},"365.03":{"start":"365.03","dur":"5.949","text":"of George Meade. it was in this capacity\nthat Ames served at the Battle of"},"370.98":{"start":"370.979","dur":"5.571","text":"Chancellorsville and probably because of\nthis connection with Meade, Ames"},"376.55":{"start":"376.55","dur":"7.28","text":"received promotion of brigadier general\nof volunteers. It&#39;s all who you know. he&#39;s 27 years"},"383.83":{"start":"383.83","dur":"6.13","text":"old he gets his first star. his new\nBrigade though was not with Meade in the"},"389.96":{"start":"389.96","dur":"4.4","text":"fifth corps. it was in the eleventh Corps\nunder general O.O. Howard. Oliver Otis Howard,"},"394.36":{"start":"394.36","dur":"6.32","text":"Francis Barlow&#39;s division, of course Ames\nbrigade. and everybody knows the story"},"400.68":{"start":"400.68","dur":"3","text":"for one reason or another -"},"404.44":{"start":"404.44","dur":"4.37","text":"which is not really the focus of this\ntalk -  ole Francis decided to take his"},"408.81":{"start":"408.81","dur":"4.88","text":"division out in front of the rest of the\nUnion line and well you can judge by the"},"413.69":{"start":"413.69","dur":"2.86","text":"map what happened next"},"416.55":{"start":"416.55","dur":"6.169","text":"right there. those georgians hot right on\nthem and scatter Barlow&#39;s division. Ames"},"422.72":{"start":"422.719","dur":"4.211","text":"is gonna be part of that. in the midst of\nthe retreat Barlow was wounded and Ames"},"426.93":{"start":"426.93","dur":"4.479","text":"assumed command of the division they\nretreated back to Cemetery Hill after"},"431.41":{"start":"431.409","dur":"3.021","text":"suffering much loss. and the next day"},"435.22":{"start":"435.219","dur":"4.711","text":"suffer further on July 2 when Ames&#39;\ndivision holding Cemetery Hill were"},"439.93":{"start":"439.93","dur":"6.489","text":"attacked by the Louisianans and the North\nCarolinians in nighttime fighting. the"},"446.42":{"start":"446.419","dur":"5.15","text":"line broke again. you can only imagine\nwhat Ames was going through his mind at"},"451.57":{"start":"451.569","dur":"4.13","text":"that time now being the division\ncommander. But his line broke again the Union"},"455.70":{"start":"455.699","dur":"5.84","text":"Army had to scratch and claw to retake\nthe position. I now have in my notes"},"461.54":{"start":"461.539","dur":"3","text":"&quot;reflection on Ames at Gettysburg.&quot;"},"467.54":{"start":"467.54","dur":"12.48","text":"yep.That&#39;s what I think about that. now in August\nAmes was transferred to the Atlantic"},"480.02":{"start":"480.02","dur":"5.07","text":"seaboard and there he commanded another\nbrigade with Quincy Gilmore&#39;s forces in"},"485.09":{"start":"485.09","dur":"4.04","text":"the attempt to take Charleston. from\nthere he went to Florida briefly before"},"489.13":{"start":"489.13","dur":"5.14","text":"returning to Virginia - This will test your\nCivil War knowledge -  as part of Ben Butler&#39;s"},"494.27":{"start":"494.27","dur":"6.44","text":"Army of the James -  there&#39;s a picture most of\nyou&#39;ve never seen -  and the newly formed"},"500.71":{"start":"500.71","dur":"10.27","text":"Corps. Ames is right there. Ames\nserved in William F. Smith forces"},"510.98":{"start":"510.98","dur":"4.96","text":"outside Richmond in what is commonly\nknown as the Bermuda Hundred campaign"},"515.94":{"start":"515.94","dur":"3","text":"and part of the siege against Forts\nHarrison and Gillmore. I believe those"},"518.94":{"start":"518.94","dur":"4.44","text":"forts are now part of Richmond\nBattlefield. in January of sixty-five"},"523.38":{"start":"523.38","dur":"4.64","text":"Ames was ordered to Wilmington, North Carolina and the impending assault on"},"528.02":{"start":"528.02","dur":"5.36","text":"Fort Fisher. arguably  this is\nAmes&#39; most important leading role in the"},"533.38":{"start":"533.38","dur":"13.42","text":"war on January 15th his division attacks the fort after heavy"},"546.80":{"start":"546.8","dur":"4.48","text":"casualties and much hand-to-hand fighting\ncaptures the place. as a result of his"},"551.28":{"start":"551.28","dur":"4.78","text":"actions he received a brevet promotion - this\nis at the end of the war -  he received a"},"556.06":{"start":"556.06","dur":"10.08","text":"brevet promotion to major general of\nvolunteers and a full promotion to"},"566.14":{"start":"566.14","dur":"7.46","text":"brigadier general in the regular army.\nvolunteer ranks  not too good to have"},"573.60":{"start":"573.6","dur":"5.31","text":"if there&#39;s not a war going on. they can\nget rid of you very easily. so to come"},"578.91":{"start":"578.91","dur":"6.74","text":"out of the war with one star in the\nregular army is not bad. Ames ended the"},"585.65":{"start":"585.65","dur":"5.29","text":"war having risen from first lieutenant\nin the regular army to a brigadier"},"590.94":{"start":"590.94","dur":"8.26","text":"general in four years. he was 29 years\nold in 1865. his war record included"},"599.20":{"start":"599.2","dur":"1.23","text":"seven major campaigns"},"600.43":{"start":"600.43","dur":"7.8","text":"16 battles in that and skirmishes\nand a record that&#39;s really not that bad."},"608.23":{"start":"608.23","dur":"8.14","text":"obviously a brave man. in the postwar\nyears Ames initially went to South"},"616.37":{"start":"616.37","dur":"5.65","text":"Carolina but in 1866 took a leave of\nabsence to travel abroad he visited"},"622.02":{"start":"622.02","dur":"6.27","text":"Germany Austria Switzerland France and\nEngland if that wasn&#39;t enough he went on"},"628.29":{"start":"628.29","dur":"12.18","text":"to Italy and back to Scotland and\nIreland. in other words, I envy him.  He just took a"},"640.47":{"start":"640.47","dur":"5.27","text":"leave of absence and traveled around. I\nget the sense - well I don&#39;t know how much -"},"645.74":{"start":"645.74","dur":"6.81","text":"I get the sense though his family - he\ncame from money. in 1867 Ames returned to"},"652.55":{"start":"652.55","dur":"4.47","text":"the USA and resumed his Army career as a\nlieutenant colonel in the 24th US"},"657.02":{"start":"657.02","dur":"6.42","text":"regiment. just because you have a star\ndoesn&#39;t mean they have a slot for you so"},"663.44":{"start":"663.44","dur":"5.58","text":"he had to take a lieutenant colonelcy\nand orders soon came for him report to"},"669.02":{"start":"669.02","dur":"3.97","text":"the fourth Military District of\nMississippi and Arkansas under General"},"672.99":{"start":"672.99","dur":"7.08","text":"E.O.C. Ord. Ames entered a completely\ndifferent world at this point. this world"},"680.07":{"start":"680.07","dur":"9.959","text":"was the era in American history called\nReconstruction now let&#39;s back up a"},"690.03":{"start":"690.029","dur":"4.81","text":"little before Ames gets there. look at the\nsituation that he enters in Mississippi."},"694.84":{"start":"694.839","dur":"6.19","text":"I want you to think about these numbers\nright here  and if this happened in your area."},"701.85":{"start":"701.85","dur":"4.75","text":"like every other southern state\nMississippi faced an economic,"},"706.60":{"start":"706.6","dur":"6.78","text":"social, and political system in upheaval.\nin the war&#39;s aftermath economically the"},"713.38":{"start":"713.38","dur":"6.43","text":"state was devastated in 1860 the\npersonal value of property including"},"719.81":{"start":"719.81","dur":"7.17","text":"slaves was 352\nmillion dollars. in 1870 ten years later"},"727.82":{"start":"727.819","dur":"7.491","text":"property was valued at 59 million .the\nvalue of real estate drop from a hundred"},"735.31":{"start":"735.31","dur":"5.389","text":"and fifty seven million to a hundred and\neighteen million and cotton production went"},"740.70":{"start":"740.699","dur":"7.421","text":"from 1.2 million bales in 1860 to 1870 when\nit was about half of that at five hundred"},"748.12":{"start":"748.12","dur":"7.25","text":"and sixty-five thousand. There&#39;s your\neconomy. socially several million"},"755.37":{"start":"755.37","dur":"5.05","text":"slaves across the South are now freedmen\nand the social order had been turned"},"760.42":{"start":"760.42","dur":"6.409","text":"upside down I think that&#39;s obvious.now\nRepublicans, the Republican, party wanted"},"766.83":{"start":"766.829","dur":"10.211","text":"these freedmen to vote Republican and all\nthe southern whites wanted them to"},"777.04":{"start":"777.04","dur":"4.049","text":"vote Democrat you see what&#39;s coming"},"781.68":{"start":"781.68","dur":"6.57","text":"you get two sides that are coming up and\nit&#39;s going to boil down"},"788.25":{"start":"788.25","dur":"4.139","text":"to race a lot of this is going to boil\ndown to a black-and-white question but"},"792.39":{"start":"792.389","dur":"4.87","text":"it all derives out of politics and\nthe machinations that are going to be coming"},"797.26":{"start":"797.259","dur":"5.45","text":"forth as you&#39;ll see. now politically\nthe state government had been"},"802.71":{"start":"802.709","dur":"7.081","text":"reconstituted under the proclamation of\nPresident Andrew Johnson. This is in 1865, 1866."},"809.79":{"start":"809.79","dur":"5.18","text":"Johnson appoints William Sharkey as\nprovisional governor and the state"},"814.97":{"start":"814.97","dur":"3.96","text":"constitutional convention repeal the\nordinance of secession and ratified the"},"818.93":{"start":"818.93","dur":"7.909","text":"Thirteenth Amendment. however they also,\nthe legislature, also passed Black Codes"},"826.84":{"start":"826.839","dur":"4.531","text":"quote-unquote which basically replaced\nthe word slave in the old laws with"},"831.37":{"start":"831.37","dur":"6.24","text":"freedmen in the new one. now these laws\nare never enacted and never put into"},"837.61":{"start":"837.61","dur":"2.42","text":"effect at least that&#39;s what I&#39;m reading\nin Mississippi. it"},"840.03":{"start":"840.03","dur":"3.66","text":"could have been in other places in the\nSouth but that&#39;s not really the point."},"843.69":{"start":"843.69","dur":"7.26","text":"the point is it went over very badly in\nthe North to have these Black Codes even"},"850.95":{"start":"850.95","dur":"5.62","text":"being voted upon in the South because\nthe Northern politicians especially the"},"856.57":{"start":"856.57","dur":"4.47","text":"Radical Republicans the ones that really\nwant to tighten the screws down on the"},"861.04":{"start":"861.04","dur":"6.55","text":"South are not liking the way that these\nblacks are being treated and they want"},"867.59":{"start":"867.59","dur":"6.52","text":"to help them as best they can of course\nthey also want them to vote Republican"},"874.11":{"start":"874.11","dur":"5.98","text":"so that&#39;s what you get. you make them indebted to you. these type of actions across"},"880.09":{"start":"880.09","dur":"7.78","text":"the South led the U S Congress to pass\nthe Civil Rights Act of 1866 President"},"887.87":{"start":"887.87","dur":"2.05","text":"Johnson"},"889.92":{"start":"889.92","dur":"5.84","text":"a political cartoon President Johnson\nvetoed the bill and congress being"},"895.76":{"start":"895.76","dur":"6.74","text":"majority Republican overrode it. Congress\neven went a step further and refused to"},"902.50":{"start":"902.5","dur":"5.29","text":"see any of the newly elected legislative\nmembers from the southern states so in"},"907.79":{"start":"907.79","dur":"4.64","text":"other words they had a vote across the\nSouth they elected these people a lot of"},"912.43":{"start":"912.43","dur":"4.03","text":"ex-Confederates, some of them ex-Confederates, and \nthey sent them back to Congress and then"},"916.46":{"start":"916.46","dur":"8.02","text":"they weren&#39;t recognized they weren&#39;t\ngiven a seat which is you know got"},"924.48":{"start":"924.48","dur":"4.31","text":"under a lot of people skins. All this\nwas the start, all this stuff was the"},"928.79":{"start":"928.79","dur":"3","text":"start of a contentious relationship\nbetween the executive and the"},"931.79":{"start":"931.79","dur":"5.17","text":"legislative branch with Johnson favoring\na more modern reconstruction plan and"},"936.96":{"start":"936.96","dur":"5.12","text":"Congress favoring a more radical one.\nRepublicans in congress able to override"},"942.08":{"start":"942.08","dur":"4.73","text":"Johnson&#39;s vetoes this historical period\nbecame known as &quot;radical reconstruction.&quot;"},"946.81":{"start":"946.81","dur":"10.38","text":"from 1865 to 1870 there are three\namendments passed that everybody in here"},"957.19":{"start":"957.19","dur":"6.36","text":"is familiar with the 13th 14th and 15th\namendment. They have been called the"},"963.55":{"start":"963.55","dur":"5.22","text":"Reconstruction Amendments. The amendments \nwere directed at ending slavery and"},"968.77":{"start":"968.77","dur":"4.59","text":"providing full citizenship\nto Freedmen. northern"},"973.36":{"start":"973.36","dur":"3.08","text":"Congressmen believe that providing black\nman with the right to vote would be the"},"976.44":{"start":"976.44","dur":"8.1","text":"most rapid means of political education\nand training. now partly because -"},"984.54":{"start":"984.54","dur":"6.46","text":"I don&#39;t know\nif we could get an amendment passed"},"991.00":{"start":"991","dur":"5.959","text":"again today. I can&#39;t think of a subject\nyou get one passed. That&#39;s how high the bar is now"},"996.96":{"start":"996.959","dur":"6.901","text":"to get an amendment to modify the\nConstitution. now partly because the"},"1003.86":{"start":"1003.86","dur":"5.36","text":"southern states refused to ratify the\n14th Amendment Congress is"},"1009.22":{"start":"1009.22","dur":"3.97","text":"going to pass the Reconstruction Acts\nwhich divided the South into five"},"1013.19":{"start":"1013.19","dur":"4.56","text":"military districts. states were required to\nratify the Fourteenth Amendment and"},"1017.75":{"start":"1017.75","dur":"5.67","text":"draft a new constitution. They had to ratify\nthe Fourteenth Amendment, most of them had ratified the"},"1023.42":{"start":"1023.42","dur":"4.669","text":"Thirteenth Amendment but not all of them, they had to\nratify it, and they had to"},"1028.09":{"start":"1028.089","dur":"4.781","text":"draft a new constitution which\nguaranteed the former slaves their"},"1032.87":{"start":"1032.87","dur":"7.67","text":"rights. How do you think this is going to go over?\nso since they wouldn&#39;t do it, military"},"1040.54":{"start":"1040.54","dur":"3.759","text":"rule is going to take over civilian\ngovernance and this is how Ames is going"},"1044.30":{"start":"1044.299","dur":"3.741","text":"to get involved here. under the\nprotection of Federal soldiers delegates"},"1048.04":{"start":"1048.04","dur":"4.31","text":"convened in Jackson to write a new state\nconstitution that would allow"},"1052.35":{"start":"1052.35","dur":"8.35","text":"Mississippi to be readmitted to the\nUnion. now I don&#39;t know - I&#39;ll take an aside ,I&#39;ll"},"1060.70":{"start":"1060.7","dur":"4.51","text":"come back to that in just a minute and\n I&#39;m  probably should"},"1065.21":{"start":"1065.21","dur":"7.26","text":"have done this earlier - this whole time\nperiod that we&#39;re going into as I said"},"1072.47":{"start":"1072.47","dur":"4.99","text":"alluded to a little bit earlier is a\nblack and white period. I mean it&#39;s"},"1077.46":{"start":"1077.46","dur":"4.95","text":"divided by race. it&#39;s black and white. and\nof course that makes me nervous to be"},"1082.41":{"start":"1082.41","dur":"3.25","text":"honest to be talking about it because\nthere&#39;s nothing good that can ever come"},"1085.66":{"start":"1085.66","dur":"5.68","text":"out of me talking about it right? because I\ncan&#39;t please everybody. I have gone out"},"1091.34":{"start":"1091.34","dur":"4.329","text":"of my way -  I&#39;m not going to talk about everything because I can&#39;t talk about"},"1095.67":{"start":"1095.669","dur":"5.75","text":"everything but I&#39;ve gone out of my way\nto make both sides look equally bad"},"1101.94":{"start":"1101.94","dur":"10.88","text":"and that is as fair as I can be so I hope\nto hit down the middle right there because"},"1112.82":{"start":"1112.82","dur":"8.209","text":"neither side is looking too good at\ntimes right here. now Mississippi is drafting"},"1121.03":{"start":"1121.029","dur":"3.191","text":"this constitution and one hundred\ndelegates were authorized for the"},"1124.22":{"start":"1124.22","dur":"10.51","text":"convention. now Mississippi contains 61\ncounties at this time with 32 of those"},"1134.73":{"start":"1134.73","dur":"6.819","text":"counties being of a black majority in\npopulation these 32 counties were given"},"1141.55":{"start":"1141.549","dur":"6.561","text":"seventy of the hundred delegates while\nthe 29 majority white counties were"},"1148.11":{"start":"1148.11","dur":"5.779","text":"given 30 delegates however it is the\nfirst time on the other end of it -"},"1153.89":{"start":"1153.889","dur":"5.13","text":"spectrum - it is the first time that black\npeople have participated as a political"},"1159.02":{"start":"1159.019","dur":"7.01","text":"body in the state of Mississippi so\nhistoric moment to say the least but"},"1166.03":{"start":"1166.029","dur":"13.551","text":"obviously they&#39;ve skewered -  its not\ndemocratic to say the least. Of the 85 delegates"},"1179.58":{"start":"1179.58","dur":"4.959","text":"there were eventually seated 17 will be\nblack 19 will be conservative that will"},"1184.54":{"start":"1184.539","dur":"7.171","text":"be the old line of white Southerners,  29 will be\nNative Republicans  - Native Republicans"},"1191.71":{"start":"1191.71","dur":"2.26","text":"meaning they will be southern people\nthat will"},"1193.97":{"start":"1193.97","dur":"7.62","text":"join the Republican party otherwise\nknown as scallywags. remember gone with the"},"1201.59":{"start":"1201.59","dur":"0.469","text":"wind?"},"1202.06":{"start":"1202.059","dur":"6.58","text":"scallywags! Scallywags - I use these\nterms it because they used them back then"},"1208.64":{"start":"1208.639","dur":"4.981","text":"but I&#39;ll use these terms and frequently - \na scallywag is a southerner who turns -"},"1213.62":{"start":"1213.62","dur":"4.86","text":"a white settler - who turned his back on\nthe white people. that&#39;s what they refer"},"1218.48":{"start":"1218.48","dur":"6.799","text":"to them as -  a scallywag. that&#39;s\na term from the era."},"1226.20":{"start":"1226.2","dur":"3.88","text":"and there were some twenty-odd\ncarpetbaggers there too. What is a"},"1230.08":{"start":"1230.08","dur":"6.52","text":"carpetbagger? A northerner who moves\nsouth. ok what is the only thing that a"},"1236.60":{"start":"1236.6","dur":"13.07","text":"texan fears? A yankee with a UHaul! I got\nthis cold. it&#39;s really hard to do jokes with"},"1249.67":{"start":"1249.67","dur":"7.65","text":"ya&#39;ll today. I&#39;ll do my best. so we got these\ncarpetbaggers coming down. Now most of"},"1257.32":{"start":"1257.32","dur":"4.32","text":"these carpetbaggers ironically were\nformer Union army officers looking for a"},"1261.64":{"start":"1261.64","dur":"3.63","text":"new living. the \nConstitutional Convention became"},"1265.27":{"start":"1265.27","dur":"7.38","text":"derogatoryaly known as the Black and Tan\nConvention. despite much extravagant"},"1272.65":{"start":"1272.65","dur":"5.06","text":"spending on the convention. \nwhat do I mean by that? they ran up the"},"1277.71":{"start":"1277.71","dur":"6.24","text":"bill they ran up the tab when they\ndidn&#39;t need to. the constitution that"},"1283.95":{"start":"1283.95","dur":"6.66","text":"they did produce guaranteed universal\nmale suffrage. on the other hand it and"},"1290.61":{"start":"1290.61","dur":"3.5","text":"this is key to understanding whats going\nto come here -the"},"1294.11":{"start":"1294.11","dur":"4.21","text":"Constitution disbarred almost everybody\nconnected with the former Confederacy"},"1298.32":{"start":"1298.32","dur":"7.33","text":"from holding office. why do you think\nthey did that? Because who was&#39;t in the"},"1305.65":{"start":"1305.65","dur":"5.96","text":"Confederate Army? see how the two sides\nare being juxtaposed against each other?"},"1312.49":{"start":"1312.49","dur":"3.93","text":"You can&#39;t blame it on"},"1316.42":{"start":"1316.42","dur":"5.85","text":"everybody but you got so many\npeople pulling different factions in"},"1322.27":{"start":"1322.27","dur":"3.11","text":"different directions all for their own\nself-centered purpose."},"1325.38":{"start":"1325.38","dur":"6.99","text":"whites blacks Republicans Democrats\nnortherners southerners. all of"},"1332.37":{"start":"1332.37","dur":"5.44","text":"that in this bowl being mixed up. we&#39;ll\nsee how it comes out. it was in this"},"1337.81":{"start":"1337.81","dur":"4.17","text":"state of affairs that Adelbert Ames - that&#39;s\npretty blue isn&#39;t it -"},"1342.97":{"start":"1342.97","dur":"6.39","text":"later Adelbert Ames is gonna come to\nMississippi. he will take over in 1868 as"},"1349.36":{"start":"1349.36","dur":"4.65","text":"provisional governor of the state but\neven his first steps started with"},"1354.01":{"start":"1354.01","dur":"9.97","text":"controversy. Can you imagine! I mean look -  Ames aside - \ntake a look at the picture! 1868"},"1363.98":{"start":"1363.98","dur":"10.4","text":"three years after the Civil War and they\nput who in charge!"},"1374.38":{"start":"1374.38","dur":"7.98","text":"You ever put salt on the slug? nothing good can\ncome out of that. Don&#39;t ever think it wasn&#39;t  intentional."},"1382.36":{"start":"1382.36","dur":"5.92","text":"upon his arrival he\nwas ordered to assume the governorship"},"1388.28":{"start":"1388.28","dur":"4.81","text":"from the civilian governor the duly\nelected governor by the name of Benjamin"},"1393.09":{"start":"1393.09","dur":"1.04","text":"G. Humphreys."},"1394.13":{"start":"1394.13","dur":"5.299","text":"Why do we know Benjamin G. Humphreys"},"1399.43":{"start":"1399.429","dur":"8.071","text":"he took over for Barksdale. right? here\nthe battlefield. I wish you could be right"},"1407.50":{"start":"1407.5","dur":"2.9","text":"here standing on this podium with me\nlike now you see all the light bulbs"},"1410.40":{"start":"1410.4","dur":"1.2","text":"going off."},"1416.68":{"start":"1416.679","dur":"10","text":"How&#39;s the audio? Audio coming through there Caitlin?\n 21st Mississippi right? he"},"1426.68":{"start":"1426.679","dur":"6.281","text":"chases the 9th Massachusetts battery all\nthe way back to the Trostle farm right"},"1432.96":{"start":"1432.96","dur":"3.4","text":"there. Mr.Eric Campbell. Every time I think\nabout the ninth Massachusetts battery I"},"1436.36":{"start":"1436.36","dur":"6.52","text":"think of Eric Campbell. anyway, B.G. Humphries, ole\nConfederate general is now the governor."},"1442.88":{"start":"1442.88","dur":"6.56","text":"this presented a problem because\nHumphries does not recognize Adelbert"},"1449.44":{"start":"1449.44","dur":"5.859","text":"Ames as the governor and Adelbert Ames\nhas been sent by the government in"},"1455.30":{"start":"1455.299","dur":"6.01","text":"Washington to assume the governorship so\nthis presented a problem for Humphries"},"1461.31":{"start":"1461.309","dur":"7.061","text":"and he wired President Johnson for his\nopinion. Humphries after he received the"},"1468.37":{"start":"1468.37","dur":"7.51","text":"response from the Present, Humphries then\ntold Ames that he wasn&#39;t leaving. quote &quot;I"},"1475.88":{"start":"1475.88","dur":"4.84","text":"must therefore&quot; Humphries replied, &quot;in view\nof my duty to the constitutional rights"},"1480.72":{"start":"1480.72","dur":"4.51","text":"of the people of Mississippi and the\ndisapproval of the President refuse to"},"1485.23":{"start":"1485.23","dur":"5.189","text":"vacate the office of Governor\nor surrender the archives and public"},"1490.42":{"start":"1490.419","dur":"4.781","text":"property until a legally qualified\nsuccessor under the constitution of"},"1495.20":{"start":"1495.2","dur":"8.94","text":"mississippi is appointed.&quot; Think he&#39;s a lawyer?\nafter much correspondence which drug"},"1504.14":{"start":"1504.14","dur":"2.38","text":"on for several weeks,"},"1506.52":{"start":"1506.52","dur":"4.909","text":"Ames finally positioned two guards\noutside the governor&#39;s office in the old capital."},"1511.43":{"start":"1511.429","dur":"4.771","text":"The ole capital still stands - one of\nthe few buildings that survived several"},"1516.20":{"start":"1516.2","dur":"5.45","text":"visits by Sherman. there&#39;s a new capital. the governor&#39;s office is"},"1521.65":{"start":"1521.65","dur":"2.74","text":"still there.there&#39;s a lot that happens in the"},"1524.39":{"start":"1524.39","dur":"3.56","text":"governor&#39;s office but they don&#39;t even\nadvertise it but every time I go into the"},"1527.95":{"start":"1527.95","dur":"4.26","text":"capital in Mississippi I think of this\nscene right here that occurred because I"},"1532.21":{"start":"1532.21","dur":"4.52","text":"don&#39;t know if it&#39;s ever happened like\nthis before or since in American"},"1536.73":{"start":"1536.73","dur":"1.6","text":"political history."},"1538.33":{"start":"1538.33","dur":"4.979","text":"Ames just decided to quit bickering with\nHumphries and he positioned two guards"},"1543.31":{"start":"1543.309","dur":"0.941","text":"outside"},"1544.25":{"start":"1544.25","dur":"8.57","text":"of the governor&#39;s office. well eventually\nHumphries had to come out of there. you"},"1552.82":{"start":"1552.82","dur":"4.42","text":"know it&#39;s not like he had his own \nkitchen in there, or a bed"},"1557.24":{"start":"1557.24","dur":"4.77","text":"or a bathroom and so he had to come\nout and when he exited the building -"},"1562.01":{"start":"1562.01","dur":"3.39","text":"excuse me - exited the office and went\nwherever he had to go and he came back"},"1565.40":{"start":"1565.4","dur":"6.73","text":"the soldiers crossed the bayonets across\nthe door and would not allow him back in"},"1572.13":{"start":"1572.13","dur":"5.97","text":"the governor&#39;s office and that&#39;s how you\nremove a governor through military force."},"1578.10":{"start":"1578.1","dur":"8.11","text":"some might argue it was a coup. Humphries\nwould argue it is a coup. now it&#39;s"},"1586.21":{"start":"1586.21","dur":"10.22","text":"still not over though because Humphries is\nstill in the mansion and he didn&#39;t appeared to be"},"1596.43":{"start":"1596.43","dur":"8.21","text":"wanting to leave their either. Ames had\nthe awkward task of moving in with"},"1604.64":{"start":"1604.64","dur":"3","text":"Humphries."},"1608.65":{"start":"1608.65","dur":"7.58","text":"I think he told Humphries he could take\nthe upstairs, he&#39;d the downstairs. when Ames"},"1616.23":{"start":"1616.23","dur":"4.26","text":"eventually asked Humphries to vacate\nHumphries infomred Ames that the"},"1620.49":{"start":"1620.49","dur":"4.08","text":"mansion was built by the taxpayers of\nthe state and he was the duly elected"},"1624.57":{"start":"1624.57","dur":"4.68","text":"constitutional governor therefore he\ndeclined to vacate until a legally"},"1629.25":{"start":"1629.25","dur":"6.97","text":"qualified successor could take his place.\non July 10th 1868 Ames&#39; patience ended,"},"1636.22":{"start":"1636.22","dur":"6.24","text":"addressing a letter to general \/\ngovernor Humphries. he stated quote &quot;you"},"1642.46":{"start":"1642.46","dur":"3.84","text":"entirely ignore the Reconstruction Acts&quot; -\nI love when they get petty in these"},"1646.30":{"start":"1646.3","dur":"4.4","text":"formal terms - &quot;you entirely ignore the\nReconstruction Acts and the"},"1650.70":{"start":"1650.7","dur":"7.46","text":"action taken by those empowered to \nact upon them. I recognize no other"},"1658.16":{"start":"1658.16","dur":"6.32","text":"authority. the feeling entertained not\nonly by me but by others not to cause"},"1664.48":{"start":"1664.48","dur":"5.92","text":"you any personal inconvenience has\nthrough your own action ceased to exist.&quot;"},"1671.97":{"start":"1671.97","dur":"5.81","text":"Ames then had a guard remove Humphries&#39;\nbelongings from the mansion and the"},"1677.78":{"start":"1677.78","dur":"4.15","text":"governor and his family were marched out\nof the mansion between a file of guards"},"1681.93":{"start":"1681.93","dur":"5.37","text":"and thus Ames officially became the\nprovisional governor of the state of"},"1687.30":{"start":"1687.3","dur":"7.04","text":"Mississippi at age 33. so you have this\nthing, if you&#39;re not picking up on it, you"},"1694.34":{"start":"1694.34","dur":"5.34","text":"have a military officer he still got his\ncommission he still active military - I&#39;ll show you his"},"1699.68":{"start":"1699.68","dur":"5.03","text":"governors portrait in just a second -\nyou&#39;ve got a military officer serving as"},"1704.71":{"start":"1704.71","dur":"5.16","text":"governor appointed by Washington over a\ncivil government. have you ever heard of"},"1709.87":{"start":"1709.87","dur":"8.49","text":"such a thing? now Ames&#39; main job -\nthere&#39;s his governors portrait. I think"},"1718.36":{"start":"1718.36","dur":"2.1","text":"that&#39;s kept in a broom closet. I"},"1720.46":{"start":"1720.46","dur":"9.26","text":"was joking there&#39;s other governors\nthey&#39;ve stuck in the broom closet."},"1729.72":{"start":"1729.72","dur":"0.9","text":"Bilbo would be up there I bet."},"1730.62":{"start":"1730.62","dur":"7.32","text":"Ames main duties were to\nmaintain peace and order and second to"},"1737.94":{"start":"1737.94","dur":"4.79","text":"oversee the re-establishment of a new\nstate government. In other words Ames"},"1742.73":{"start":"1742.73","dur":"7.03","text":"is supposed to keep the machine running\nand make sure that the government -"},"1749.76":{"start":"1749.76","dur":"4.12","text":"they are able to form a government - \nwhich will comply with the"},"1753.88":{"start":"1753.88","dur":"5.97","text":"Reconstruction Acts. the voters though had\nother ideas and instantly threw him"},"1759.85":{"start":"1759.85","dur":"5.62","text":"the first curve ball when they rejected\nthe new state constitution drafted by"},"1765.47":{"start":"1765.47","dur":"4.13","text":"the quote-unquote &quot;black and tan\nconvention&quot; which I talked about earlier."},"1771.25":{"start":"1771.25","dur":"3.57","text":"voter fraud and intimidation was alleged\nbut it&#39;s hard to separate fact from"},"1774.82":{"start":"1774.82","dur":"3.36","text":"fiction as to what exactly happened."},"1778.18":{"start":"1778.18","dur":"4.09","text":"For his own slef, Ames thought \nthat mississippians had rejected the"},"1782.27":{"start":"1782.27","dur":"4.3","text":"Constitution because blacks were given\nthe right to vote and most former"},"1786.57":{"start":"1786.57","dur":"5.12","text":"Confederates were disenfranchised. that\nwas his opinion. nevertheless Mississippi"},"1791.69":{"start":"1791.69","dur":"4.34","text":"had not complied with the requirements\nfor readmission and Mississippi became,"},"1796.03":{"start":"1796.03","dur":"6.62","text":"along with Texas and Virginia, the \n&quot;last unreconstructed States.&quot; upon Ulysses"},"1802.65":{"start":"1802.65","dur":"4.57","text":"S. Grant&#39;s election as President, Ames was now\nappointed, in addition to being"},"1807.22":{"start":"1807.22","dur":"5.81","text":"governor, as the new military commander\nthe fourth Military District."},"1813.03":{"start":"1813.03","dur":"5.77","text":"Congress now stipulated that all\nofficeholders in Mississippi had to take"},"1818.80":{"start":"1818.8","dur":"5.11","text":"the &quot;iron-clad oath of allegiance&quot;\nor be removed from office."},"1824.88":{"start":"1824.88","dur":"7.4","text":"Ames was given free rein to appoint\nwho he chose to every position and"},"1832.28":{"start":"1832.28","dur":"6.03","text":"&quot;loyal men&quot; at that. I want\nyou to think about these statistics I&#39;m"},"1838.31":{"start":"1838.31","dur":"6.92","text":"about to give you and one person having\nthis much power at 33. Ames"},"1845.23":{"start":"1845.23","dur":"7.05","text":"removed and appointed 60 sheriffs, 72\ncircuit and probate clerks, 60 county"},"1852.28":{"start":"1852.28","dur":"0.74","text":"assessors,"},"1853.02":{"start":"1853.02","dur":"5.61","text":"50 mayors, 220\nalderman, 385"},"1858.63":{"start":"1858.63","dur":"2.11","text":"justices of the peace,"},"1860.74":{"start":"1860.74","dur":"4.56","text":"165 constables,\n370 members of the"},"1865.30":{"start":"1865.3","dur":"7.71","text":"board of Police, 40 coroners, 20 surveyors\n25 city marshals ,and more than"},"1873.01":{"start":"1873.01","dur":"7.47","text":"300 election registrars and even such\nminor officials as school Commissioner,"},"1880.48":{"start":"1880.48","dur":"3.3","text":"city collector, superintendents of the\npoor, etc."},"1883.78":{"start":"1883.78","dur":"6.74","text":"can you imagine having that much\npatronage power in a little state like"},"1890.52":{"start":"1890.52","dur":"6.27","text":"that? the problem though with\nreconstituting the government is where"},"1896.79":{"start":"1896.79","dur":"8.32","text":"do you find competent people to step in\nthere that are going to be ethical and"},"1905.11":{"start":"1905.11","dur":"5.55","text":"competent? where do you find those? because\nall of the white southerners are what?"},"1910.66":{"start":"1910.66","dur":"7.14","text":"they&#39;re not gonna take it. they won&#39;t\ntake the oath. and all the blacks they&#39;ve"},"1917.80":{"start":"1917.8","dur":"6.27","text":"received no education - for generations\nhave received no education so who does"},"1924.07":{"start":"1924.07","dur":"6.48","text":"that leave you? that leaves you a lot of\nwhite northerners who come in and blacks."},"1930.55":{"start":"1930.55","dur":"4.84","text":"they put blacks in there also. now he\nhad to rely on the recommendation of"},"1935.39":{"start":"1935.39","dur":"3.66","text":"others for so many appointments and in\nmany instances I think he was deceived"},"1939.05":{"start":"1939.05","dur":"6.08","text":"in this ladies and gentleman though for\nbetter or worse is how the carpetbaggers"},"1945.13":{"start":"1945.13","dur":"5.52","text":"gain power over the state and local\ngovernment which eventually led to graft"},"1950.65":{"start":"1950.65","dur":"4.97","text":"and corruption which in turn resulted in\npersecution, fraudulent elections and"},"1955.62":{"start":"1955.62","dur":"7.52","text":"finally elections. now before I go to \ncarpetbaggers I might point out right"},"1963.14":{"start":"1963.14","dur":"0.91","text":"here"},"1964.05":{"start":"1964.05","dur":"4.34","text":"a lot of  you have  heard me refer to it right\nthere ladies and gentlemen is Houston,"},"1968.39":{"start":"1968.39","dur":"8.35","text":"Mississippi. ok now when my mother went into\nlabor they had to drive - to show you I have"},"1976.74":{"start":"1976.74","dur":"3.4","text":"always been connected to the National\nPark Service -"},"1980.14":{"start":"1980.14","dur":"4.89","text":"my mother and father had to drive the\nNatchez Trace at eighty miles an hour,"},"1985.03":{"start":"1985.03","dur":"1.74","text":"some say a hundred,"},"1986.77":{"start":"1986.77","dur":"4.68","text":"that&#39;s because - I was the first\nchild - my mother sat up all night reading"},"1991.45":{"start":"1991.45","dur":"5.49","text":"a book trying to figure out if she was\nin labor or not. so when the Sun came up her"},"1996.94":{"start":"1996.94","dur":"5.49","text":"mother-in-law my father&#39;s mother told\nher for goodness sake go to the hospital"},"2002.43":{"start":"2002.43","dur":"5.82","text":"so to be connected with the Park Service\nthey got on the Natchez Trace Parkway"},"2008.25":{"start":"2008.25","dur":"9.54","text":"and did a hundred miles an hour all the\nway up to Tupelo where I was born on April 27 1971."},"2019.33":{"start":"2019.33","dur":"10.94","text":"this is also the place where we used to - \nHouston is still a small town all the"},"2030.27":{"start":"2030.27","dur":"4.08","text":"people used to go up to Tupelo for your\nFriday and Saturday nights - that&#39;s where you used to"},"2034.35":{"start":"2034.35","dur":"5.48","text":"to take your dates and so forth. And on the\nNatchez Trace I actually had a date get so"},"2039.83":{"start":"2039.83","dur":"5.69","text":"mad at me that she got out of the car on\nthe Natchez Trace and I said to her as I stood"},"2045.52":{"start":"2045.52","dur":"3.649","text":"beside the door she was walking down the\nparkway I said I don&#39;t think you have"},"2049.17":{"start":"2049.169","dur":"6.5","text":"anywhere to go. she\neventually got back in the car and we"},"2055.67":{"start":"2055.669","dur":"3.26","text":"had a lovely evening."},"2058.93":{"start":"2058.929","dur":"8.39","text":"For Okolona and the rest of Chickasaw County, I refer\nyou to the Nathan Bedford Forrest"},"2067.32":{"start":"2067.319","dur":"8.25","text":"lecture. I think it has more stories on\nthere. ok so what&#39;s this right here? Carpetbag."},"2075.57":{"start":"2075.569","dur":"2.09","text":"What&#39;s this right here? Carpetbagger."},"2077.66":{"start":"2077.659","dur":"8.381","text":"oh yes look at him!  now does anybody know who , and I don&#39;t\nknow why this is, but does anybody know who that is?"},"2086.04":{"start":"2086.04","dur":"8.809","text":"Audience member: Carl Shurz. Was he here? Audience member: oh yes. He became - I&#39;m looking through all"},"2094.85":{"start":"2094.849","dur":"4.49","text":"these political cartoons and I am not really\nlooking for political cartoons but I put"},"2099.34":{"start":"2099.339","dur":"5.5","text":"in like subject in the into Google and I search for images and Carl Schurz"},"2104.84":{"start":"2104.839","dur":"5.5","text":"comes up as a symbol time and again of\ncarpetbaggers and I guess I think he was"},"2110.34":{"start":"2110.339","dur":"7.341","text":"in charge of the Freedmen throughout the\nSouth, not Mississippi. and he became I guess"},"2117.68":{"start":"2117.68","dur":"2.72","text":"that symbol right there"},"2120.40":{"start":"2120.4","dur":"8.36","text":"I&#39;m sure he didn&#39;t like the\nlikeness. now Ames also had the issue back"},"2128.76":{"start":"2128.76","dur":"5.96","text":"in Mississippi of the freed slaves to\ndeal with. now Ames lowered"},"2134.72":{"start":"2134.72","dur":"5.7","text":"the poll tax to include more people. he\nalso declared Freedmen competent to"},"2140.42":{"start":"2140.42","dur":"4.98","text":"stand as jurors in the state which was a\nhuge deal, this was a big step,"},"2145.96":{"start":"2145.96","dur":"4.19","text":"a big dea, andl it was due to Ames&#39;\nconvictions that it was done."},"2150.15":{"start":"2150.15","dur":"7.469","text":"Thomas Nast political cartoon there. due\nto Ames overseeing a statewide election"},"2157.62":{"start":"2157.619","dur":"4.591","text":"in 1869 the Mississippi legislature\nconvened for the first time since the"},"2162.21":{"start":"2162.21","dur":"5.31","text":"rule of Radical Reconstruction began in\n1869 and nothing to find the social"},"2167.52":{"start":"2167.52","dur":"5.599","text":"revolution that was happening more\nthan the Legislature&#39;s composition that"},"2173.12":{"start":"2173.119","dur":"4.271","text":"year. some of the former richest counties\nin Mississippi were now represented by"},"2177.39":{"start":"2177.39","dur":"7.04","text":"former slaves and the Speaker of the\nHouse was from New York. they quickly"},"2184.43":{"start":"2184.43","dur":"3","text":"ratified the 14th and 15th Amendment."},"2189.13":{"start":"2189.13","dur":"6.35","text":"Events quickly followed. in 1870 as was\nthe custom at the time - I didn&#39;t know"},"2195.48":{"start":"2195.48","dur":"6.029","text":"this until researching this - the\nstate legislature back then elected the"},"2201.51":{"start":"2201.509","dur":"9.991","text":"Senators. Did you know that?  [mumbling from audience]"},"2238.29":{"start":"2238.289","dur":"3.04","text":"pay close attention to this if you can\nread the writing up there - I know it&#39;s"},"2241.33":{"start":"2241.329","dur":"3.671","text":"not the clearest shot - but read real\nquickly of what that actual document is"},"2245.00":{"start":"2245","dur":"4.73","text":"right there because it&#39;s going to go in.\nthis is the document certifying"},"2250.71":{"start":"2250.71","dur":"5.319","text":"Adelbert Ames down here the governor of\nMississippi that Hiram Revels has"},"2256.03":{"start":"2256.029","dur":"5.51","text":"been elected to the Senate. he&#39;s certifying\nthe election. keep that in mind because I"},"2261.54":{"start":"2261.539","dur":"4.27","text":"couldn&#39;t find the copy that I really\nneeded but the document that I will refer to in"},"2265.81":{"start":"2265.809","dur":"10.911","text":"just a second had to look exactly like\nthis. now Hiram Revels at that time is elected"},"2276.72":{"start":"2276.72","dur":"4.599","text":"to the US Senate along with Adlebert Ames by the legislature in 1870."},"2281.32":{"start":"2281.319","dur":"5.76","text":"they were\nfulfilling unfinished terms from prior"},"2287.08":{"start":"2287.079","dur":"6.02","text":"to the Civil War. their terms began on\nFebruary 24, 1870.  Hiram revels is an"},"2293.10":{"start":"2293.099","dur":"4.281","text":"interesting character. he first came to\nMississippi as a chaplain of a black"},"2297.38":{"start":"2297.38","dur":"5.76","text":"regiment USCT in 1866 he moved in\nNatchez and helped set up free schools"},"2303.14":{"start":"2303.14","dur":"4.939","text":"across the state. he became the first\nblack man to serve in the United States"},"2308.08":{"start":"2308.079","dur":"9.96","text":"Senate also taking the place of the \nunexpired term of Jefferson Davis."},"2319.60":{"start":"2319.6","dur":"6.54","text":"now legend has it I&#39;ve never been able\nto pin down but reportedly Senator"},"2326.14":{"start":"2326.14","dur":"4.42","text":"Davis told one of his colleagues when he\nleft the Senate that if Mississippi ever"},"2330.56":{"start":"2330.56","dur":"5.75","text":"returned a representative to the United\nStates Senate that it would be a black"},"2336.31":{"start":"2336.31","dur":"6.98","text":"man. and so that was prophetic there.\nThomas Nast - it&#39;s a very good likeness of"},"2343.29":{"start":"2343.29","dur":"15.59","text":"Hiram Revels and I think that is Schurz. now ironically Ames"},"2358.88":{"start":"2358.88","dur":"5.81","text":"experienced, not Revels, Ames experienced\nmore trouble getting seated in the"},"2364.69":{"start":"2364.69","dur":"5.78","text":"Senate then Hiram Revels. as provisional\nmilitary governor of Mississippi"},"2370.47":{"start":"2370.47","dur":"6.56","text":"Ames certified his own election to the\nSenate and guess what?"},"2377.82":{"start":"2377.82","dur":"7.32","text":"in parliamentary things the Senate\nsomebody quickly raised an objection that"},"2385.14":{"start":"2385.14","dur":"6.59","text":"Ames could not certify his own election.\nand so here we go. you can imagine I&#39;ve"},"2391.73":{"start":"2391.73","dur":"3.6","text":"never understood all the inner workings\nof the Senate. they can pull out some"},"2395.33":{"start":"2395.33","dur":"7.32","text":"arcane rules. but it took\nseveral weeks for Ames to get seated in"},"2402.65":{"start":"2402.65","dur":"7.56","text":"the Senate. Nevertheless, throughout his\nSenate tenure, Ames was still played"},"2410.21":{"start":"2410.21","dur":"4.32","text":"despite being seeded by charges that he was"},"2414.53":{"start":"2414.53","dur":"7.12","text":"never duly elected to the Senate. it was\na mistake by Adelbert to nominate"},"2421.65":{"start":"2421.65","dur":"6.83","text":"himself to be the Senator. he should have\nknown better. I guess"},"2428.48":{"start":"2428.48","dur":"4.53","text":"his ego got the better of him. with\nthe influence he exercised over the"},"2433.01":{"start":"2433.01","dur":"4.68","text":"legislature the fact he owned no real\nproperty in the state he paid no taxes"},"2437.69":{"start":"2437.69","dur":"4.43","text":"and held no allegiance to the people of\nMississippi it made him a very poor"},"2442.12":{"start":"2442.12","dur":"6.29","text":"choice to be Senator. but eventually this\nwas worked out and Ames was"},"2448.41":{"start":"2448.41","dur":"4.04","text":"admitted to the Senate. he became known,\ndespite not"},"2452.45":{"start":"2452.45","dur":"5.27","text":"starting, this way he became known as a\ngood speaker and a debater. to back up a"},"2457.72":{"start":"2457.72","dur":"6.43","text":"little bit though while he waited to be\nseated he occupied himself by wisely"},"2464.15":{"start":"2464.15","dur":"11.01","text":"courting the daughter of Benjamin Butler.\nYa&#39;ll familiar with Benjamin Butler? I can&#39;t"},"2475.16":{"start":"2475.16","dur":"12.07","text":"believe that! She&#39;s pretty. you know the thing they\nactually - I couldn&#39;t find a"},"2487.23":{"start":"2487.23","dur":"4.53","text":"a copy - but in one of the books that I\nwas researching here, one of the"},"2491.76":{"start":"2491.76","dur":"4.81","text":"newspaper correspondents you know how\nthey used to sketch things as they were"},"2496.57":{"start":"2496.57","dur":"6.45","text":"happening, the newspaper correspondent was\nsitting in the galleries of the"},"2503.02":{"start":"2503.02","dur":"5.66","text":"the Andrew Johnson impeachment trial and\nhe was sitting across the aisle and he"},"2508.68":{"start":"2508.68","dur":"6.76","text":"actually sketched Ames and Blanche Butler\ncourting, talking to each other. you know"},"2515.44":{"start":"2515.44","dur":"4.04","text":"she was sitting in the pew in front,"},"2519.48":{"start":"2519.48","dur":"3.849","text":"and she was turned around\ntalking to him. that was the first time"},"2523.33":{"start":"2523.329","dur":"6.891","text":"they had met and she made such a direct\nimpact on Adelbert Ames -"},"2530.22":{"start":"2530.22","dur":"5.04","text":"impression is a better word - that he\nnever forgot her and he would come back"},"2535.26":{"start":"2535.26","dur":"3.75","text":"to Washington as much as he could so\nthat might have something to"},"2539.01":{"start":"2539.01","dur":"5.88","text":"do with him wanting to be in the Senate. might not have been about power"},"2544.89":{"start":"2544.89","dur":"4.979","text":"after all. they were married in 1871\nand they would eventually have six"},"2549.87":{"start":"2549.869","dur":"8.091","text":"children together. with the expiration of\nHiram Revels&#39; term, James L. Alcorn is"},"2557.96":{"start":"2557.96","dur":"5.09","text":"going to take his seat. now Alcorn is an\ninteresting figure he&#39;s going to take a"},"2563.05":{"start":"2563.05","dur":"4.309","text":"seat beside Ames. he&#39;s a native Mississippian.\nhe served briefly in the Confederate"},"2567.36":{"start":"2567.359","dur":"5.451","text":"Army before returning home and he lost\ntwo boys to the war fighting for the"},"2572.81":{"start":"2572.81","dur":"3.47","text":"Confederacy including one that came\nhome"},"2576.28":{"start":"2576.28","dur":"3.539","text":"partially a deaf and a drunk."},"2583.00":{"start":"2583","dur":"12.55","text":"He probably needed counciling. On\nhis grave, Alcorn, James L. Alcorn would"},"2595.55":{"start":"2595.55","dur":"7.5","text":"write the following epitaph, &quot;that he died\nfrom the insane war of the"},"2603.05":{"start":"2603.05","dur":"10.53","text":"rebellion.&quot; probably his son died of PTSD.\nwar drove him insane. he committed suicide"},"2613.58":{"start":"2613.58","dur":"6.35","text":"in 1879. Alcorn said he never was the same  after the war."},"2619.93":{"start":"2619.93","dur":"9.3","text":"despite being a Mississippian, Senator Alcorn became a scallywag, quickly joined"},"2629.23":{"start":"2629.23","dur":"4.6","text":"in the Republican ranks, and after\nserving as governor from 1869 to 1871"},"2633.83":{"start":"2633.83","dur":"6.19","text":"was elected to the Senate. Alcorn though \nbecomes the leader of the moderate"},"2640.02":{"start":"2640.02","dur":"3.64","text":"faction of the Mississippi Republicans\nwhile Ames becomes the head of the more"},"2643.66":{"start":"2643.66","dur":"5.01","text":"radical faction. despite being on the\nsame team, the two were gonna clash often"},"2648.67":{"start":"2648.67","dur":"3.85","text":"in the Senate so much so that both men\ndecided to run for governor of"},"2652.52":{"start":"2652.52","dur":"6.17","text":"Mississippi in 1872. Ames was supported\nby African-Americans and the"},"2658.69":{"start":"2658.69","dur":"4.63","text":"Carpetbaggers while Alcorn was supported\nby conservative whites and the"},"2663.32":{"start":"2663.32","dur":"10.93","text":"scallywags. Ames won handedly by a vote\nof 69,872 to 50,490."},"2674.25":{"start":"2674.25","dur":"4.5","text":"With Ames&#39; election\nthe Republican led legislature in"},"2678.75":{"start":"2678.75","dur":"5.04","text":"Mississippi promptly raised the millage\nrate -  how many of you are getting ready"},"2683.79":{"start":"2683.79","dur":"8.09","text":"for your taxes right now? the legislature,\nnot Ames, the legislature promptly raised"},"2691.88":{"start":"2691.88","dur":"10.01","text":"the millage rate to 14 mills. my home\ncounty of Chickasaw where Houston is had"},"2701.89":{"start":"2701.89","dur":"8.59","text":"a county millage rate of 20. this act\nbasically meant confiscation to say the"},"2710.48":{"start":"2710.48","dur":"5.31","text":"least. I mean you can&#39;t pay it so if\nyou&#39;ve got somebody, if you want wealth"},"2715.79":{"start":"2715.79","dur":"5.9","text":"redistribution, how do you do that? you\ncan&#39;t legally go and take somebody&#39;s"},"2721.69":{"start":"2721.69","dur":"6.63","text":"property. As long as they pay the taxes you\ncan&#39;t do that. so what"},"2728.32":{"start":"2728.32","dur":"1.43","text":"do you do?"},"2729.75":{"start":"2729.75","dur":"5.99","text":"jack the taxes up so far that these\nplanters who own 1,000, 2,000 acres, these"},"2735.74":{"start":"2735.74","dur":"5.27","text":"big planters, they can&#39;t hold it anymore\nbecause they can&#39;t afford it. how"},"2741.01":{"start":"2741.01","dur":"4.34","text":"many of you thought about that when you\nbought your house? do I want all this"},"2745.35":{"start":"2745.35","dur":"6.11","text":"land? do I want to pay taxes on this land\nright here? also interesting to note is"},"2751.46":{"start":"2751.46","dur":"5.04","text":"you look at the years right here - you got\nSouth Carolina, you got Mississippi, you got"},"2756.50":{"start":"2756.5","dur":"4.72","text":"the years running down through here, you\ncan see how they go up directly until"},"2761.22":{"start":"2761.22","dur":"7.39","text":"Ames is elected governor, and then you will\nsee that they start to drop back down"},"2768.61":{"start":"2768.61","dur":"5.15","text":"as soon as Ames can get them back down.\nbut you can basically double all those"},"2773.76":{"start":"2773.76","dur":"6.21","text":"mill rates when you put in the local\ntaxes. now in addition to that the poll"},"2779.97":{"start":"2779.97","dur":"6.84","text":"tax was increased from $2 to $6 and\nwhite employers were made responsible"},"2786.81":{"start":"2786.81","dur":"7.05","text":"for paying for their black laborers.\ncotton was taxed at $10 a bail and the"},"2793.86":{"start":"2793.86","dur":"7.52","text":"money had to go to the Freedmen&#39;s bank. the\nlegislature even imposed a 1%"},"2801.38":{"start":"2801.38","dur":"5.35","text":"tax on travel. how they ever collected\nthat I don&#39;t know. the property owner"},"2806.73":{"start":"2806.73","dur":"5.18","text":"simply couldn&#39;t pay these taxes and 6.4 million acres of land"},"2811.91":{"start":"2811.91","dur":"6.88","text":"ended up being confiscated. 6.4 million acres. Now what would you do?"},"2818.79":{"start":"2818.79","dur":"9.21","text":"take race out of it, put race in it. what would\nyou do if you were in that position? It is"},"2828.00":{"start":"2828","dur":"6.74","text":"not an easy subject to deal with, to\nthink about, but what would you do? you have"},"2834.74":{"start":"2834.74","dur":"3","text":"no representation if you are a white southerner."},"2840.14":{"start":"2840.14","dur":"7.76","text":"Then\nagain, what would you do if you were a"},"2847.90":{"start":"2847.9","dur":"5.41","text":"black southerner? don&#39;t you think you come\nout of the war as a freed slave, don&#39;t"},"2853.31":{"start":"2853.31","dur":"6.51","text":"you think you&#39;re owed something? you&#39;re\nthe one that built it with your labor."},"2859.82":{"start":"2859.82","dur":"7.99","text":"now the citizens petition the\nlegislature to reduce the millage rate"},"2867.81":{"start":"2867.81","dur":"3.81","text":"but it fell upon deaf ears and this\nreally set the course for the white"},"2871.62":{"start":"2871.62","dur":"4.31","text":"taxpayer revolt that followed. To Ames&#39;\ncredit, he did have the"},"2875.93":{"start":"2875.93","dur":"3.5","text":"millage rate lowered and in the subsequent\nyears with all the graft and corruption"},"2879.43":{"start":"2879.43","dur":"1.78","text":"that was alleged in the state,"},"2881.21":{"start":"2881.21","dur":"5.64","text":"Ames was never accused of any\nembezzlement. Ames was never happy in"},"2886.85":{"start":"2886.85","dur":"3.73","text":"Mississippi though. his family remained\nin the north and he returned there"},"2890.58":{"start":"2890.58","dur":"5.78","text":"periodically for weeks at a time.when he was gone he was not"},"2896.36":{"start":"2896.36","dur":"4.89","text":"served well by the Lieutenant Governor, a\nguy by the name of Alexander K. Davis one"},"2901.25":{"start":"2901.25","dur":"3.81","text":"time when Ames went North, Davis\ndischarged all the employees at the"},"2905.06":{"start":"2905.06","dur":"7.68","text":"capital and put his friends in. he dismissed the\nGovernor&#39;s private secretary and then"},"2912.74":{"start":"2912.74","dur":"4.22","text":"proceeded to appoint several judges. in\none month."},"2917.55":{"start":"2917.55","dur":"5.58","text":"Lieutenant Governor Davis issued 34\npardons, 6 remissions of forfeiture, 6"},"2923.13":{"start":"2923.13","dur":"5.56","text":"commutations of sentence.Davis was later"},"2928.69":{"start":"2928.69","dur":"5.42","text":"accused of taking a bribe in at least\none case, probably a lot of them. Ames was"},"2934.11":{"start":"2934.11","dur":"5.46","text":"beyond reproach in these matters but the\naction still smeared his administration."},"2939.57":{"start":"2939.57","dur":"6.22","text":"In other words, he&#39;s getting blamed. on\nthe local government level much graft"},"2945.79":{"start":"2945.79","dur":"4.62","text":"and corruption was taking place also. all\nthe things I&#39;ve described came to a head"},"2950.41":{"start":"2950.41","dur":"6.86","text":"in September of 1874 in a place called\nVicksburg, Mississippi. this story boils"},"2957.27":{"start":"2957.27","dur":"2.19","text":"down the two things at work here:"},"2959.46":{"start":"2959.46","dur":"7.57","text":"race and taxes. almost all the elected\nofficials were black and the taxation"},"2967.03":{"start":"2967.03","dur":"5.61","text":"rate was 14 mills for the state, 14 for\nthe county, and for the municipal"},"2972.64":{"start":"2972.64","dur":"0.93","text":"authorities it was 21.5."},"2973.57":{"start":"2973.57","dur":"7.94","text":"the county and \ncity debt that stood at 13,000 in 1869 now"},"2981.51":{"start":"2981.51","dur":"4.01","text":"stood according to one congressional\nhearing witness at 1.4"},"2985.52":{"start":"2985.52","dur":"3.32","text":"million in five years."},"2988.84":{"start":"2988.84","dur":"4.98","text":"it went from 13,000 to1.4 million. in those times the"},"2993.82":{"start":"2993.82","dur":"4.25","text":"sheriff wielded extraordinary power and\nhe picked the composition of juries and"},"2998.07":{"start":"2998.07","dur":"4.85","text":"collected the state and local taxes. in\nVicksburg there was a sheriff named"},"3002.92":{"start":"3002.92","dur":"4.97","text":"Peter Crosby and he was alleged to have\nembezzled"},"3007.89":{"start":"3007.89","dur":"4.9","text":"thousands of tax dollars and\ndid not have a bond to cover his duties"},"3012.79":{"start":"3012.79","dur":"7.29","text":"as a tax collector anyway. now Peter\nCrosby is black and the local whites"},"3020.08":{"start":"3020.08","dur":"5.61","text":"organized a Taxpayers League for the\n1874 election and won the county"},"3025.69":{"start":"3025.69","dur":"6.06","text":"seats. now they turned their attention on\nthe sheriff who was still in office. he"},"3031.75":{"start":"3031.75","dur":"4.53","text":"hadn&#39;t run for re-election in that term. at\na meeting reportedly 500 strong"},"3036.28":{"start":"3036.28","dur":"5.36","text":"they drafted a resolution calling on\nCrosby to resign the message was sent to"},"3041.64":{"start":"3041.64","dur":"4.93","text":"the courthouse and the reply was soon\nreceive from Crosby saying he wasn&#39;t"},"3046.57":{"start":"3046.57","dur":"5.69","text":"leaving. the Taxpayers League then\nmarched on the courthouse and made him"},"3052.26":{"start":"3052.26","dur":"9.04","text":"another offer. at this point he resigned.\nas provisional military governor Ames had"},"3061.30":{"start":"3061.3","dur":"5.8","text":"become used to being able to call on US\ntroops for any disturbances. but in 1874"},"3067.10":{"start":"3067.1","dur":"4.21","text":"he didn&#39;t have any troops at his\ndisposal. he had militia. and that"},"3071.31":{"start":"3071.31","dur":"4.31","text":"militia was composed of both black\ncompanies and white companies. upon"},"3075.62":{"start":"3075.62","dur":"5.46","text":"hearing the news of Crosby&#39;s removal\nAmes sent orders to the local black militia"},"3081.08":{"start":"3081.08","dur":"8.05","text":"company to suppress the riots. You see what is coming? he did not tell the white"},"3089.13":{"start":"3089.13","dur":"2.57","text":"companies of his plans"},"3091.70":{"start":"3091.7","dur":"3.93","text":"reasoning they wouldn&#39;t obey his orders\nanyway - probably right."},"3095.63":{"start":"3095.63","dur":"4.98","text":"meanwhile on that Sunday December 6 the news\nspread in the black churches and they"},"3100.61":{"start":"3100.61","dur":"5.45","text":"determined to march upon Vicksburg in\nsupport of the sheriff."},"3106.97":{"start":"3106.97","dur":"3.16","text":"Now white Vicksburgians armed themselves."},"3110.13":{"start":"3110.13","dur":"9.35","text":"black freedmen armed themselves. and now\na posse comitatus was in effect. near the"},"3119.48":{"start":"3119.48","dur":"4.6","text":"present-day surrender monument along the\nold battlefield of Vicksburg, the 2 sides"},"3124.08":{"start":"3124.08","dur":"7.03","text":"bumped into each other and shooting\nbegan and when it ended 2 whites and 29"},"3131.11":{"start":"3131.11","dur":"1.11","text":"blacks were dead."},"3132.22":{"start":"3132.22","dur":"6.24","text":"subsequently federal troops were sent by\nthe district military commander, at that"},"3138.46":{"start":"3138.46","dur":"5.43","text":"time Phil Sheridan, to restore order\nand return Crosby to office. but ill will"},"3143.89":{"start":"3143.89","dur":"4.88","text":"was still felt toward Ames who was\naccused of setting the fuse that started"},"3148.77":{"start":"3148.77","dur":"5.17","text":"the whole thing. you know I&#39;ve thought\nabout it putting this program together - I don&#39;t know"},"3153.94":{"start":"3153.94","dur":"6.75","text":"what he was supposed to do. I mean\nwhere do you even start tackling that"},"3160.69":{"start":"3160.69","dur":"5.13","text":"Vicksburg story. Do you\nsupport Crosby, do you support the Taxpayers"},"3165.82":{"start":"3165.82","dur":"5.05","text":"League? if you support Crosby who do you\nturn to support Crosby? I mean who did he"},"3170.87":{"start":"3170.87","dur":"6.35","text":"have? What were his options? I don&#39;t know. It\nlooks like he was in a no-win situation"},"3177.22":{"start":"3177.22","dur":"8.82","text":"there, whatever he chose to do. in 1875\nwhite Democrats began to implement"},"3186.04":{"start":"3186.04","dur":"4.56","text":"&quot;the mississippi plan&quot; to take back the\nstate government. armed groups of"},"3190.60":{"start":"3190.6","dur":"4.33","text":"vigilantes known as the Red Shirts, the\nDemocratic shooting club - I like that"},"3194.93":{"start":"3194.93","dur":"5.65","text":"Democratic shooting club - the White club, etc.\n used economic and political"},"3200.58":{"start":"3200.58","dur":"4.46","text":"pressure to keep white and black\nRepublicans away from the polls. there"},"3205.04":{"start":"3205.04","dur":"4.25","text":"were race riots in Yazoo City and Rolling Fort with the largest occurring in"},"3209.29":{"start":"3209.29","dur":"7.9","text":"Clinton. Ames appealed to President Grant\nfor troops but Grant fearing the result in"},"3217.19":{"start":"3217.19","dur":"4.5","text":"the upcoming election and their\npotential impact didn&#39;t send any troops"},"3221.69":{"start":"3221.69","dur":"6","text":"to help the Governor. Ames called out\nthe militia or the only militia that he"},"3227.69":{"start":"3227.69","dur":"4.13","text":"thought would honor his orders and once\nagain these black militia companies"},"3231.82":{"start":"3231.82","dur":"4.22","text":"marching around the countryside in\nMississippi just sent the the anger"},"3236.04":{"start":"3236.04","dur":"4.28","text":"soaring among the white population and\nonly a quick agreement"},"3240.32":{"start":"3240.32","dur":"5.05","text":"for fair elections between the\nDemocrats and Ames prevented a bloody"},"3245.37":{"start":"3245.37","dur":"6.12","text":"outcome and a possible coup. Fair\nelections didn&#39;t happen. I think that&#39;s"},"3251.49":{"start":"3251.49","dur":"5.58","text":"gonna be pretty obvious. so a Republican\nmajority of 30,000 votes in 1874"},"3257.07":{"start":"3257.07","dur":"7.2","text":"elections flipped to a 30,000\nvote majority for the Democrats within"},"3264.27":{"start":"3264.27","dur":"1.86","text":"two years."},"3266.13":{"start":"3266.13","dur":"6.48","text":"flush with a Democratic majority in the 1876\nlegislature the body promptly drew up"},"3272.61":{"start":"3272.61","dur":"5.24","text":"impeachment charges against Ames. they\ncharged him responsibility for the"},"3277.85":{"start":"3277.85","dur":"3.29","text":"Vicksburg riots and the illegal part in\njudicial appointments when the Senate"},"3281.14":{"start":"3281.14","dur":"8.73","text":"was out of session, etc.. a trial\ncommenced but before it got well under way"},"3289.87":{"start":"3289.87","dur":"3.66","text":"an agreement was reached whereby the\nlegislature would draw all the charges"},"3293.53":{"start":"3293.53","dur":"8.27","text":"and then Ames would resign. he agreed. in\nother words Ames would not resign that"},"3301.80":{"start":"3301.8","dur":"5.62","text":"governorship while impeachment charges\nwere being held against him. legislature had"},"3307.42":{"start":"3307.42","dur":"5.32","text":"to drop him and then he would leave. what\nchoice did he have?"},"3312.74":{"start":"3312.74","dur":"4.48","text":"The charges were pretty flimsey to say the least, but the votes"},"3317.22":{"start":"3317.22","dur":"3","text":"were there. he was going to get impeached."},"3321.48":{"start":"3321.48","dur":"12.13","text":"Ames is going to live until 1933 the\nlast full-ranking general from the"},"3333.61":{"start":"3333.61","dur":"6.74","text":"American Civil War. Ya&#39;ll don&#39;t like that? that&#39;s the best\npart of the whole program!"},"3341.51":{"start":"3341.509","dur":"11.41","text":"I&#39;ll end with Ames&#39; own words. It&#39;s kind of neat when you live so\nlong you can help defend your"},"3352.92":{"start":"3352.919","dur":"5.961","text":"legacy. in 1900 professor James Garner\nwrote Ames regarding his time in"},"3358.88":{"start":"3358.88","dur":"6.509","text":"Mississippi and Ames responded in the\nfollowing: &quot;you ask"},"3365.39":{"start":"3365.389","dur":"4.79","text":"what I consider some of the merits of\nyour administration in Mississippi&quot; -  Garner"},"3370.18":{"start":"3370.179","dur":"7.6","text":"asking Ames to tell him\nwhat he did good while he was there - &quot;my"},"3377.78":{"start":"3377.779","dur":"4.62","text":"dear professor when you appear before\nSt. Peter at the gates of Heaven"},"3383.12":{"start":"3383.119","dur":"4.48","text":"what can you say in reply to a query as\n &#39;as to the merits of your earthly"},"3387.60":{"start":"3387.599","dur":"5.88","text":"career? To say I acted\nconscienciously to the"},"3393.48":{"start":"3393.479","dur":"5.78","text":"best of my ability does not seem to be\nsufficient. to say that I did not saddle"},"3399.26":{"start":"3399.259","dur":"3.92","text":"the state with the debt of millions on\naccount of railroads and other like"},"3403.18":{"start":"3403.179","dur":"4.91","text":"enterprises that might have done and as was done in other states"},"3408.09":{"start":"3408.089","dur":"6.15","text":"will be a claim of merit no honest man\ncould make."},"3414.24":{"start":"3414.239","dur":"6.52","text":"yet you know I am credited with\nthat merit by my political opponents. as"},"3420.76":{"start":"3420.759","dur":"4.69","text":"men&#39;s lives are generally consistent and\nas I was honest and conscientious in"},"3425.45":{"start":"3425.449","dur":"5.74","text":"financial affairs how could I be\notherwise in other affairs? no doubt it"},"3431.19":{"start":"3431.189","dur":"6.58","text":"is true I did not appoint to office the\nbest men in the state but it is no less"},"3437.77":{"start":"3437.769","dur":"6.73","text":"true that the best men in the state\nwould not take the office at my hand. I"},"3444.50":{"start":"3444.499","dur":"10.56","text":"hold I appointed the best men available.\ncould I do more?&quot; in closing I ask you to"},"3455.06":{"start":"3455.059","dur":"6.42","text":"look over the course of events during\nAmes&#39; tenure in Mississippi. what would"},"3461.48":{"start":"3461.479","dur":"6.47","text":"you do in his shoes? what would you do if\nyou were a black citizen? what would you"},"3467.95":{"start":"3467.949","dur":"5.471","text":"do if were a white citizen? do you find"},"3473.42":{"start":"3473.42","dur":"11.5","text":"the people of Mississippi to\nbe right? wrong? neutral. They are hard questions to answer."},"3484.92":{"start":"3484.92","dur":"5.949","text":"I don&#39;t have an answer because I&#39;m only the\nstoryteller. but when you go out of here"},"3490.87":{"start":"3490.869","dur":"6.47","text":"hopefully we will never have another\nsituation in this country where we have"},"3497.34":{"start":"3497.339","dur":"6.96","text":"to go through an ordeal, a trial,\ntribulations if you will, where this"},"3504.30":{"start":"3504.299","dur":"3.991","text":"country has to come out on the other\nside and spill so much blood in order to"},"3508.29":{"start":"3508.29","dur":"2.279","text":"do so."},"3510.57":{"start":"3510.569","dur":"4.311","text":"It&#39;s a heavy cost and it didn&#39;t stop with the\nCivil War to say the least."},"3515.96":{"start":"3515.96","dur":"1.119","text":"thank you very much."}}